<?xml version="1.0" encoding="utf-8"?>
<query>
<id>12</id>
<streaminfo>
<stream>
<streamid>1</streamid>
<streamspecificquerylength>4</streamspecificquerylength>
</stream>
<stream>
<streamid>2</streamid>
<streamspecificquerylength>4</streamspecificquerylength>
</stream>
<stream>
<streamid>3</streamid>
<streamspecificquerylength>4</streamspecificquerylength>
</stream>
</streaminfo>
<terminfo>
<termnum>4</termnum>
<term>
<termid>1</termid>
<word>descript</word>
<stream>
<streamid>1</streamid>
<streamfrequency>215</streamfrequency>
<streamtermfrequency>215</streamtermfrequency>
</stream>
<stream>
<streamid>2</streamid>
<streamfrequency>1294</streamfrequency>
<streamtermfrequency>1425</streamtermfrequency>
</stream>
<stream>
<streamid>3</streamid>
<streamfrequency>1479</streamfrequency>
<streamtermfrequency>1640</streamtermfrequency>
</stream>
</term>
<term>
<termid>2</termid>
<word>injuri</word>
<stream>
<streamid>1</streamid>
<streamfrequency>4271</streamfrequency>
<streamtermfrequency>4347</streamtermfrequency>
</stream>
<stream>
<streamid>2</streamid>
<streamfrequency>9941</streamfrequency>
<streamtermfrequency>23113</streamtermfrequency>
</stream>
<stream>
<streamid>3</streamid>
<streamfrequency>11241</streamfrequency>
<streamtermfrequency>27460</streamtermfrequency>
</stream>
</term>
<term>
<termid>3</termid>
<word>cult</word>
<stream>
<streamid>1</streamid>
<streamfrequency>3</streamfrequency>
<streamtermfrequency>3</streamtermfrequency>
</stream>
<stream>
<streamid>2</streamid>
<streamfrequency>7</streamfrequency>
<streamtermfrequency>12</streamtermfrequency>
</stream>
<stream>
<streamid>3</streamid>
<streamfrequency>9</streamfrequency>
<streamtermfrequency>15</streamtermfrequency>
</stream>
</term>
<term>
<termid>4</termid>
<word>activ</word>
<stream>
<streamid>1</streamid>
<streamfrequency>10126</streamfrequency>
<streamtermfrequency>10623</streamtermfrequency>
</stream>
<stream>
<streamid>2</streamid>
<streamfrequency>41932</streamfrequency>
<streamtermfrequency>93394</streamtermfrequency>
</stream>
<stream>
<streamid>3</streamid>
<streamfrequency>43780</streamfrequency>
<streamtermfrequency>104017</streamtermfrequency>
</stream>
</term>
</terminfo>
<docinfo>
<docnum>84</docnum>
<doc>
<docid>326501</docid>
<label>0</label>
<stream>
<streamid>1</streamid>
<length>5</length>
<uniquelength>5</uniquelength>
<term>
<termid>1</termid>
<termfrequency>0</termfrequency>
</term>
<term>
<termid>2</termid>
<termfrequency>0</termfrequency>
</term>
<term>
<termid>3</termid>
<termfrequency>0</termfrequency>
</term>
<term>
<termid>4</termid>
<termfrequency>1</termfrequency>
</term>
</stream>
<stream>
<streamid>2</streamid>
<length>64</length>
<uniquelength>53</uniquelength>
<term>
<termid>1</termid>
<termfrequency>0</termfrequency>
</term>
<term>
<termid>2</termid>
<termfrequency>2</termfrequency>
</term>
<term>
<termid>3</termid>
<termfrequency>1</termfrequency>
</term>
<term>
<termid>4</termid>
<termfrequency>2</termfrequency>
</term>
</stream>
<stream>
<streamid>3</streamid>
<length>69</length>
<uniquelength>54</uniquelength>
<term>
<termid>1</termid>
<termfrequency>0</termfrequency>
</term>
<term>
<termid>2</termid>
<termfrequency>2</termfrequency>
</term>
<term>
<termid>3</termid>
<termfrequency>1</termfrequency>
</term>
<term>
<termid>4</termid>
<termfrequency>3</termfrequency>
</term>
</stream>
</doc>
<doc>
<docid>301269</docid>
<label>0</label>
<stream>
<streamid>1</streamid>
<length>5</length>
<uniquelength>5</uniquelength>
<term>
<termid>1</termid>
<termfrequency>0</termfrequency>
</term>
<term>
<termid>2</termid>
<termfrequency>0</termfrequency>
</term>
<term>
<termid>3</termid>
<termfrequency>0</termfrequency>
</term>
<term>
<termid>4</termid>
<termfrequency>0</termfrequency>
</term>
</stream>
<stream>
<streamid>2</streamid>
<length>108</length>
<uniquelength>82</uniquelength>
<term>
<termid>1</termid>
<termfrequency>0</termfrequency>
</term>
<term>
<termid>2</termid>
<termfrequency>0</termfrequency>
</term>
<term>
<termid>3</termid>
<termfrequency>5</termfrequency>
</term>
<term>
<termid>4</termid>
<termfrequency>0</termfrequency>
</term>
</stream>
<stream>
<streamid>3</streamid>
<length>113</length>
<uniquelength>82</uniquelength>
<term>
<termid>1</termid>
<termfrequency>0</termfrequency>
</term>
<term>
<termid>2</termid>
<termfrequency>0</termfrequency>
</term>
<term>
<termid>3</termid>
<termfrequency>5</termfrequency>
</term>
<term>
<termid>4</termid>
<termfrequency>0</termfrequency>
</term>
</stream>
</doc>
<doc>
<docid>307163</docid>
<label>2</label>
<stream>
<streamid>1</streamid>
<length>4</length>
<uniquelength>4</uniquelength>
<term>
<termid>1</termid>
<termfrequency>0</termfrequency>
</term>
<term>
<termid>2</termid>
<termfrequency>0</termfrequency>
</term>
<term>
<termid>3</termid>
<termfrequency>1</termfrequency>
</term>
<term>
<termid>4</termid>
<termfrequency>0</termfrequency>
</term>
</stream>
<stream>
<streamid>2</streamid>
<length>0</length>
<uniquelength>0</uniquelength>
<term>
<termid>1</termid>
<termfrequency>0</termfrequency>
</term>
<term>
<termid>2</termid>
<termfrequency>0</termfrequency>
</term>
<term>
<termid>3</termid>
<termfrequency>0</termfrequency>
</term>
<term>
<termid>4</termid>
<termfrequency>0</termfrequency>
</term>
</stream>
<stream>
<streamid>3</streamid>
<length>4</length>
<uniquelength>4</uniquelength>
<term>
<termid>1</termid>
<termfrequency>0</termfrequency>
</term>
<term>
<termid>2</termid>
<termfrequency>0</termfrequency>
</term>
<term>
<termid>3</termid>
<termfrequency>1</termfrequency>
</term>
<term>
<termid>4</termid>
<termfrequency>0</termfrequency>
</term>
</stream>
</doc>
<doc>
<docid>294599</docid>
<label>2</label>
<stream>
<streamid>1</streamid>
<length>7</length>
<uniquelength>7</uniquelength>
<term>
<termid>1</termid>
<termfrequency>0</termfrequency>
</term>
<term>
<termid>2</termid>
<termfrequency>0</termfrequency>
</term>
<term>
<termid>3</termid>
<termfrequency>1</termfrequency>
</term>
<term>
<termid>4</termid>
<termfrequency>0</termfrequency>
</term>
</stream>
<stream>
<streamid>2</streamid>
<length>0</length>
<uniquelength>0</uniquelength>
<term>
<termid>1</termid>
<termfrequency>0</termfrequency>
</term>
<term>
<termid>2</termid>
<termfrequency>0</termfrequency>
</term>
<term>
<termid>3</termid>
<termfrequency>0</termfrequency>
</term>
<term>
<termid>4</termid>
<termfrequency>0</termfrequency>
</term>
</stream>
<stream>
<streamid>3</streamid>
<length>7</length>
<uniquelength>7</uniquelength>
<term>
<termid>1</termid>
<termfrequency>0</termfrequency>
</term>
<term>
<termid>2</termid>
<termfrequency>0</termfrequency>
</term>
<term>
<termid>3</termid>
<termfrequency>1</termfrequency>
</term>
<term>
<termid>4</termid>
<termfrequency>0</termfrequency>
</term>
</stream>
</doc>
<doc>
<docid>257920</docid>
<label>2</label>
<stream>
<streamid>1</streamid>
<length>6</length>
<uniquelength>6</uniquelength>
<term>
<termid>1</termid>
<termfrequency>0</termfrequency>
</term>
<term>
<termid>2</termid>
<termfrequency>0</termfrequency>
</term>
<term>
<termid>3</termid>
<termfrequency>1</termfrequency>
</term>
<term>
<termid>4</termid>
<termfrequency>0</termfrequency>
</term>
</stream>
<stream>
<streamid>2</streamid>
<length>50</length>
<uniquelength>43</uniquelength>
<term>
<termid>1</termid>
<termfrequency>0</termfrequency>
</term>
<term>
<termid>2</termid>
<termfrequency>0</termfrequency>
</term>
<term>
<termid>3</termid>
<termfrequency>1</termfrequency>
</term>
<term>
<termid>4</termid>
<termfrequency>0</termfrequency>
</term>
</stream>
<stream>
<streamid>3</streamid>
<length>56</length>
<uniquelength>45</uniquelength>
<term>
<termid>1</termid>
<termfrequency>0</termfrequency>
</term>
<term>
<termid>2</termid>
<termfrequency>0</termfrequency>
</term>
<term>
<termid>3</termid>
<termfrequency>2</termfrequency>
</term>
<term>
<termid>4</termid>
<termfrequency>0</termfrequency>
</term>
</stream>
</doc>
<doc>
<docid>209378</docid>
<label>0</label>
<stream>
<streamid>1</streamid>
<length>2</length>
<uniquelength>2</uniquelength>
<term>
<termid>1</termid>
<termfrequency>0</termfrequency>
</term>
<term>
<termid>2</termid>
<termfrequency>0</termfrequency>
</term>
<term>
<termid>3</termid>
<termfrequency>0</termfrequency>
</term>
<term>
<termid>4</termid>
<termfrequency>0</termfrequency>
</term>
</stream>
<stream>
<streamid>2</streamid>
<length>66</length>
<uniquelength>54</uniquelength>
<term>
<termid>1</termid>
<termfrequency>0</termfrequency>
</term>
<term>
<termid>2</termid>
<termfrequency>0</termfrequency>
</term>
<term>
<termid>3</termid>
<termfrequency>1</termfrequency>
</term>
<term>
<termid>4</termid>
<termfrequency>1</termfrequency>
</term>
</stream>
<stream>
<streamid>3</streamid>
<length>68</length>
<uniquelength>55</uniquelength>
<term>
<termid>1</termid>
<termfrequency>0</termfrequency>
</term>
<term>
<termid>2</termid>
<termfrequency>0</termfrequency>
</term>
<term>
<termid>3</termid>
<termfrequency>1</termfrequency>
</term>
<term>
<termid>4</termid>
<termfrequency>1</termfrequency>
</term>
</stream>
</doc>
<doc>
<docid>336844</docid>
<label>0</label>
<stream>
<streamid>1</streamid>
<length>12</length>
<uniquelength>12</uniquelength>
<term>
<termid>1</termid>
<termfrequency>0</termfrequency>
</term>
<term>
<termid>2</termid>
<termfrequency>0</termfrequency>
</term>
<term>
<termid>3</termid>
<termfrequency>0</termfrequency>
</term>
<term>
<termid>4</termid>
<termfrequency>0</termfrequency>
</term>
</stream>
<stream>
<streamid>2</streamid>
<length>39</length>
<uniquelength>36</uniquelength>
<term>
<termid>1</termid>
<termfrequency>0</termfrequency>
</term>
<term>
<termid>2</termid>
<termfrequency>0</termfrequency>
</term>
<term>
<termid>3</termid>
<termfrequency>1</termfrequency>
</term>
<term>
<termid>4</termid>
<termfrequency>0</termfrequency>
</term>
</stream>
<stream>
<streamid>3</streamid>
<length>51</length>
<uniquelength>41</uniquelength>
<term>
<termid>1</termid>
<termfrequency>0</termfrequency>
</term>
<term>
<termid>2</termid>
<termfrequency>0</termfrequency>
</term>
<term>
<termid>3</termid>
<termfrequency>1</termfrequency>
</term>
<term>
<termid>4</termid>
<termfrequency>0</termfrequency>
</term>
</stream>
</doc>
<doc>
<docid>231294</docid>
<label>0</label>
<stream>
<streamid>1</streamid>
<length>13</length>
<uniquelength>13</uniquelength>
<term>
<termid>1</termid>
<termfrequency>0</termfrequency>
</term>
<term>
<termid>2</termid>
<termfrequency>0</termfrequency>
</term>
<term>
<termid>3</termid>
<termfrequency>0</termfrequency>
</term>
<term>
<termid>4</termid>
<termfrequency>0</termfrequency>
</term>
</stream>
<stream>
<streamid>2</streamid>
<length>117</length>
<uniquelength>75</uniquelength>
<term>
<termid>1</termid>
<termfrequency>0</termfrequency>
</term>
<term>
<termid>2</termid>
<termfrequency>0</termfrequency>
</term>
<term>
<termid>3</termid>
<termfrequency>2</termfrequency>
</term>
<term>
<termid>4</termid>
<termfrequency>0</termfrequency>
</term>
</stream>
<stream>
<streamid>3</streamid>
<length>130</length>
<uniquelength>77</uniquelength>
<term>
<termid>1</termid>
<termfrequency>0</termfrequency>
</term>
<term>
<termid>2</termid>
<termfrequency>0</termfrequency>
</term>
<term>
<termid>3</termid>
<termfrequency>2</termfrequency>
</term>
<term>
<termid>4</termid>
<termfrequency>0</termfrequency>
</term>
</stream>
</doc>
<doc>
<docid>172739</docid>
<label>0</label>
<stream>
<streamid>1</streamid>
<length>7</length>
<uniquelength>7</uniquelength>
<term>
<termid>1</termid>
<termfrequency>0</termfrequency>
</term>
<term>
<termid>2</termid>
<termfrequency>0</termfrequency>
</term>
<term>
<termid>3</termid>
<termfrequency>0</termfrequency>
</term>
<term>
<termid>4</termid>
<termfrequency>0</termfrequency>
</term>
</stream>
<stream>
<streamid>2</streamid>
<length>67</length>
<uniquelength>50</uniquelength>
<term>
<termid>1</termid>
<termfrequency>0</termfrequency>
</term>
<term>
<termid>2</termid>
<termfrequency>0</termfrequency>
</term>
<term>
<termid>3</termid>
<termfrequency>1</termfrequency>
</term>
<term>
<termid>4</termid>
<termfrequency>0</termfrequency>
</term>
</stream>
<stream>
<streamid>3</streamid>
<length>74</length>
<uniquelength>52</uniquelength>
<term>
<termid>1</termid>
<termfrequency>0</termfrequency>
</term>
<term>
<termid>2</termid>
<termfrequency>0</termfrequency>
</term>
<term>
<termid>3</termid>
<termfrequency>1</termfrequency>
</term>
<term>
<termid>4</termid>
<termfrequency>0</termfrequency>
</term>
</stream>
</doc>
<doc>
<docid>299372</docid>
<label>0</label>
<stream>
<streamid>1</streamid>
<length>6</length>
<uniquelength>5</uniquelength>
<term>
<termid>1</termid>
<termfrequency>0</termfrequency>
</term>
<term>
<termid>2</termid>
<termfrequency>1</termfrequency>
</term>
<term>
<termid>3</termid>
<termfrequency>0</termfrequency>
</term>
<term>
<termid>4</termid>
<termfrequency>0</termfrequency>
</term>
</stream>
<stream>
<streamid>2</streamid>
<length>132</length>
<uniquelength>79</uniquelength>
<term>
<termid>1</termid>
<termfrequency>0</termfrequency>
</term>
<term>
<termid>2</termid>
<termfrequency>8</termfrequency>
</term>
<term>
<termid>3</termid>
<termfrequency>0</termfrequency>
</term>
<term>
<termid>4</termid>
<termfrequency>0</termfrequency>
</term>
</stream>
<stream>
<streamid>3</streamid>
<length>138</length>
<uniquelength>81</uniquelength>
<term>
<termid>1</termid>
<termfrequency>0</termfrequency>
</term>
<term>
<termid>2</termid>
<termfrequency>9</termfrequency>
</term>
<term>
<termid>3</termid>
<termfrequency>0</termfrequency>
</term>
<term>
<termid>4</termid>
<termfrequency>0</termfrequency>
</term>
</stream>
</doc>
<doc>
<docid>140094</docid>
<label>0</label>
<stream>
<streamid>1</streamid>
<length>5</length>
<uniquelength>5</uniquelength>
<term>
<termid>1</termid>
<termfrequency>0</termfrequency>
</term>
<term>
<termid>2</termid>
<termfrequency>0</termfrequency>
</term>
<term>
<termid>3</termid>
<termfrequency>0</termfrequency>
</term>
<term>
<termid>4</termid>
<termfrequency>0</termfrequency>
</term>
</stream>
<stream>
<streamid>2</streamid>
<length>56</length>
<uniquelength>45</uniquelength>
<term>
<termid>1</termid>
<termfrequency>1</termfrequency>
</term>
<term>
<termid>2</termid>
<termfrequency>0</termfrequency>
</term>
<term>
<termid>3</termid>
<termfrequency>0</termfrequency>
</term>
<term>
<termid>4</termid>
<termfrequency>0</termfrequency>
</term>
</stream>
<stream>
<streamid>3</streamid>
<length>61</length>
<uniquelength>47</uniquelength>
<term>
<termid>1</termid>
<termfrequency>1</termfrequency>
</term>
<term>
<termid>2</termid>
<termfrequency>0</termfrequency>
</term>
<term>
<termid>3</termid>
<termfrequency>0</termfrequency>
</term>
<term>
<termid>4</termid>
<termfrequency>0</termfrequency>
</term>
</stream>
</doc>
<doc>
<docid>178883</docid>
<label>0</label>
<stream>
<streamid>1</streamid>
<length>3</length>
<uniquelength>3</uniquelength>
<term>
<termid>1</termid>
<termfrequency>0</termfrequency>
</term>
<term>
<termid>2</termid>
<termfrequency>0</termfrequency>
</term>
<term>
<termid>3</termid>
<termfrequency>0</termfrequency>
</term>
<term>
<termid>4</termid>
<termfrequency>0</termfrequency>
</term>
</stream>
<stream>
<streamid>2</streamid>
<length>124</length>
<uniquelength>93</uniquelength>
<term>
<termid>1</termid>
<termfrequency>1</termfrequency>
</term>
<term>
<termid>2</termid>
<termfrequency>0</termfrequency>
</term>
<term>
<termid>3</termid>
<termfrequency>0</termfrequency>
</term>
<term>
<termid>4</termid>
<termfrequency>1</termfrequency>
</term>
</stream>
<stream>
<streamid>3</streamid>
<length>127</length>
<uniquelength>95</uniquelength>
<term>
<termid>1</termid>
<termfrequency>1</termfrequency>
</term>
<term>
<termid>2</termid>
<termfrequency>0</termfrequency>
</term>
<term>
<termid>3</termid>
<termfrequency>0</termfrequency>
</term>
<term>
<termid>4</termid>
<termfrequency>1</termfrequency>
</term>
</stream>
</doc>
<doc>
<docid>111102</docid>
<label>1</label>
<stream>
<streamid>1</streamid>
<length>17</length>
<uniquelength>17</uniquelength>
<term>
<termid>1</termid>
<termfrequency>0</termfrequency>
</term>
<term>
<termid>2</termid>
<termfrequency>0</termfrequency>
</term>
<term>
<termid>3</termid>
<termfrequency>0</termfrequency>
</term>
<term>
<termid>4</termid>
<termfrequency>0</termfrequency>
</term>
</stream>
<stream>
<streamid>2</streamid>
<length>47</length>
<uniquelength>42</uniquelength>
<term>
<termid>1</termid>
<termfrequency>0</termfrequency>
</term>
<term>
<termid>2</termid>
<termfrequency>1</termfrequency>
</term>
<term>
<termid>3</termid>
<termfrequency>0</termfrequency>
</term>
<term>
<termid>4</termid>
<termfrequency>0</termfrequency>
</term>
</stream>
<stream>
<streamid>3</streamid>
<length>64</length>
<uniquelength>55</uniquelength>
<term>
<termid>1</termid>
<termfrequency>0</termfrequency>
</term>
<term>
<termid>2</termid>
<termfrequency>1</termfrequency>
</term>
<term>
<termid>3</termid>
<termfrequency>0</termfrequency>
</term>
<term>
<termid>4</termid>
<termfrequency>0</termfrequency>
</term>
</stream>
</doc>
<doc>
<docid>6669</docid>
<label>0</label>
<stream>
<streamid>1</streamid>
<length>7</length>
<uniquelength>7</uniquelength>
<term>
<termid>1</termid>
<termfrequency>0</termfrequency>
</term>
<term>
<termid>2</termid>
<termfrequency>0</termfrequency>
</term>
<term>
<termid>3</termid>
<termfrequency>0</termfrequency>
</term>
<term>
<termid>4</termid>
<termfrequency>0</termfrequency>
</term>
</stream>
<stream>
<streamid>2</streamid>
<length>91</length>
<uniquelength>66</uniquelength>
<term>
<termid>1</termid>
<termfrequency>0</termfrequency>
</term>
<term>
<termid>2</termid>
<termfrequency>0</termfrequency>
</term>
<term>
<termid>3</termid>
<termfrequency>0</termfrequency>
</term>
<term>
<termid>4</termid>
<termfrequency>1</termfrequency>
</term>
</stream>
<stream>
<streamid>3</streamid>
<length>98</length>
<uniquelength>66</uniquelength>
<term>
<termid>1</termid>
<termfrequency>0</termfrequency>
</term>
<term>
<termid>2</termid>
<termfrequency>0</termfrequency>
</term>
<term>
<termid>3</termid>
<termfrequency>0</termfrequency>
</term>
<term>
<termid>4</termid>
<termfrequency>1</termfrequency>
</term>
</stream>
</doc>
<doc>
<docid>300531</docid>
<label>0</label>
<stream>
<streamid>1</streamid>
<length>5</length>
<uniquelength>5</uniquelength>
<term>
<termid>1</termid>
<termfrequency>0</termfrequency>
</term>
<term>
<termid>2</termid>
<termfrequency>0</termfrequency>
</term>
<term>
<termid>3</termid>
<termfrequency>0</termfrequency>
</term>
<term>
<termid>4</termid>
<termfrequency>0</termfrequency>
</term>
</stream>
<stream>
<streamid>2</streamid>
<length>94</length>
<uniquelength>70</uniquelength>
<term>
<termid>1</termid>
<termfrequency>0</termfrequency>
</term>
<term>
<termid>2</termid>
<termfrequency>0</termfrequency>
</term>
<term>
<termid>3</termid>
<termfrequency>0</termfrequency>
</term>
<term>
<termid>4</termid>
<termfrequency>1</termfrequency>
</term>
</stream>
<stream>
<streamid>3</streamid>
<length>99</length>
<uniquelength>71</uniquelength>
<term>
<termid>1</termid>
<termfrequency>0</termfrequency>
</term>
<term>
<termid>2</termid>
<termfrequency>0</termfrequency>
</term>
<term>
<termid>3</termid>
<termfrequency>0</termfrequency>
</term>
<term>
<termid>4</termid>
<termfrequency>1</termfrequency>
</term>
</stream>
</doc>
<doc>
<docid>55786</docid>
<label>0</label>
<stream>
<streamid>1</streamid>
<length>5</length>
<uniquelength>5</uniquelength>
<term>
<termid>1</termid>
<termfrequency>0</termfrequency>
</term>
<term>
<termid>2</termid>
<termfrequency>0</termfrequency>
</term>
<term>
<termid>3</termid>
<termfrequency>0</termfrequency>
</term>
<term>
<termid>4</termid>
<termfrequency>0</termfrequency>
</term>
</stream>
<stream>
<streamid>2</streamid>
<length>101</length>
<uniquelength>76</uniquelength>
<term>
<termid>1</termid>
<termfrequency>0</termfrequency>
</term>
<term>
<termid>2</termid>
<termfrequency>0</termfrequency>
</term>
<term>
<termid>3</termid>
<termfrequency>0</termfrequency>
</term>
<term>
<termid>4</termid>
<termfrequency>1</termfrequency>
</term>
</stream>
<stream>
<streamid>3</streamid>
<length>106</length>
<uniquelength>76</uniquelength>
<term>
<termid>1</termid>
<termfrequency>0</termfrequency>
</term>
<term>
<termid>2</termid>
<termfrequency>0</termfrequency>
</term>
<term>
<termid>3</termid>
<termfrequency>0</termfrequency>
</term>
<term>
<termid>4</termid>
<termfrequency>1</termfrequency>
</term>
</stream>
</doc>
<doc>
<docid>55787</docid>
<label>0</label>
<stream>
<streamid>1</streamid>
<length>6</length>
<uniquelength>6</uniquelength>
<term>
<termid>1</termid>
<termfrequency>0</termfrequency>
</term>
<term>
<termid>2</termid>
<termfrequency>0</termfrequency>
</term>
<term>
<termid>3</termid>
<termfrequency>0</termfrequency>
</term>
<term>
<termid>4</termid>
<termfrequency>0</termfrequency>
</term>
</stream>
<stream>
<streamid>2</streamid>
<length>111</length>
<uniquelength>81</uniquelength>
<term>
<termid>1</termid>
<termfrequency>0</termfrequency>
</term>
<term>
<termid>2</termid>
<termfrequency>0</termfrequency>
</term>
<term>
<termid>3</termid>
<termfrequency>0</termfrequency>
</term>
<term>
<termid>4</termid>
<termfrequency>1</termfrequency>
</term>
</stream>
<stream>
<streamid>3</streamid>
<length>117</length>
<uniquelength>81</uniquelength>
<term>
<termid>1</termid>
<termfrequency>0</termfrequency>
</term>
<term>
<termid>2</termid>
<termfrequency>0</termfrequency>
</term>
<term>
<termid>3</termid>
<termfrequency>0</termfrequency>
</term>
<term>
<termid>4</termid>
<termfrequency>1</termfrequency>
</term>
</stream>
</doc>
<doc>
<docid>290320</docid>
<label>0</label>
<stream>
<streamid>1</streamid>
<length>7</length>
<uniquelength>7</uniquelength>
<term>
<termid>1</termid>
<termfrequency>0</termfrequency>
</term>
<term>
<termid>2</termid>
<termfrequency>0</termfrequency>
</term>
<term>
<termid>3</termid>
<termfrequency>0</termfrequency>
</term>
<term>
<termid>4</termid>
<termfrequency>0</termfrequency>
</term>
</stream>
<stream>
<streamid>2</streamid>
<length>131</length>
<uniquelength>94</uniquelength>
<term>
<termid>1</termid>
<termfrequency>0</termfrequency>
</term>
<term>
<termid>2</termid>
<termfrequency>0</termfrequency>
</term>
<term>
<termid>3</termid>
<termfrequency>0</termfrequency>
</term>
<term>
<termid>4</termid>
<termfrequency>1</termfrequency>
</term>
</stream>
<stream>
<streamid>3</streamid>
<length>138</length>
<uniquelength>96</uniquelength>
<term>
<termid>1</termid>
<termfrequency>0</termfrequency>
</term>
<term>
<termid>2</termid>
<termfrequency>0</termfrequency>
</term>
<term>
<termid>3</termid>
<termfrequency>0</termfrequency>
</term>
<term>
<termid>4</termid>
<termfrequency>1</termfrequency>
</term>
</stream>
</doc>
<doc>
<docid>80745</docid>
<label>0</label>
<stream>
<streamid>1</streamid>
<length>12</length>
<uniquelength>12</uniquelength>
<term>
<termid>1</termid>
<termfrequency>0</termfrequency>
</term>
<term>
<termid>2</termid>
<termfrequency>0</termfrequency>
</term>
<term>
<termid>3</termid>
<termfrequency>0</termfrequency>
</term>
<term>
<termid>4</termid>
<termfrequency>0</termfrequency>
</term>
</stream>
<stream>
<streamid>2</streamid>
<length>67</length>
<uniquelength>57</uniquelength>
<term>
<termid>1</termid>
<termfrequency>0</termfrequency>
</term>
<term>
<termid>2</termid>
<termfrequency>0</termfrequency>
</term>
<term>
<termid>3</termid>
<termfrequency>0</termfrequency>
</term>
<term>
<termid>4</termid>
<termfrequency>0</termfrequency>
</term>
</stream>
<stream>
<streamid>3</streamid>
<length>79</length>
<uniquelength>57</uniquelength>
<term>
<termid>1</termid>
<termfrequency>0</termfrequency>
</term>
<term>
<termid>2</termid>
<termfrequency>0</termfrequency>
</term>
<term>
<termid>3</termid>
<termfrequency>0</termfrequency>
</term>
<term>
<termid>4</termid>
<termfrequency>0</termfrequency>
</term>
</stream>
</doc>
<doc>
<docid>15009</docid>
<label>0</label>
<stream>
<streamid>1</streamid>
<length>11</length>
<uniquelength>11</uniquelength>
<term>
<termid>1</termid>
<termfrequency>0</termfrequency>
</term>
<term>
<termid>2</termid>
<termfrequency>0</termfrequency>
</term>
<term>
<termid>3</termid>
<termfrequency>0</termfrequency>
</term>
<term>
<termid>4</termid>
<termfrequency>0</termfrequency>
</term>
</stream>
<stream>
<streamid>2</streamid>
<length>69</length>
<uniquelength>61</uniquelength>
<term>
<termid>1</termid>
<termfrequency>0</termfrequency>
</term>
<term>
<termid>2</termid>
<termfrequency>0</termfrequency>
</term>
<term>
<termid>3</termid>
<termfrequency>0</termfrequency>
</term>
<term>
<termid>4</termid>
<termfrequency>0</termfrequency>
</term>
</stream>
<stream>
<streamid>3</streamid>
<length>80</length>
<uniquelength>62</uniquelength>
<term>
<termid>1</termid>
<termfrequency>0</termfrequency>
</term>
<term>
<termid>2</termid>
<termfrequency>0</termfrequency>
</term>
<term>
<termid>3</termid>
<termfrequency>0</termfrequency>
</term>
<term>
<termid>4</termid>
<termfrequency>0</termfrequency>
</term>
</stream>
</doc>
<doc>
<docid>111297</docid>
<label>0</label>
<stream>
<streamid>1</streamid>
<length>4</length>
<uniquelength>4</uniquelength>
<term>
<termid>1</termid>
<termfrequency>0</termfrequency>
</term>
<term>
<termid>2</termid>
<termfrequency>0</termfrequency>
</term>
<term>
<termid>3</termid>
<termfrequency>0</termfrequency>
</term>
<term>
<termid>4</termid>
<termfrequency>0</termfrequency>
</term>
</stream>
<stream>
<streamid>2</streamid>
<length>75</length>
<uniquelength>54</uniquelength>
<term>
<termid>1</termid>
<termfrequency>0</termfrequency>
</term>
<term>
<termid>2</termid>
<termfrequency>0</termfrequency>
</term>
<term>
<termid>3</termid>
<termfrequency>0</termfrequency>
</term>
<term>
<termid>4</termid>
<termfrequency>0</termfrequency>
</term>
</stream>
<stream>
<streamid>3</streamid>
<length>79</length>
<uniquelength>54</uniquelength>
<term>
<termid>1</termid>
<termfrequency>0</termfrequency>
</term>
<term>
<termid>2</termid>
<termfrequency>0</termfrequency>
</term>
<term>
<termid>3</termid>
<termfrequency>0</termfrequency>
</term>
<term>
<termid>4</termid>
<termfrequency>0</termfrequency>
</term>
</stream>
</doc>
<doc>
<docid>87286</docid>
<label>0</label>
<stream>
<streamid>1</streamid>
<length>4</length>
<uniquelength>4</uniquelength>
<term>
<termid>1</termid>
<termfrequency>0</termfrequency>
</term>
<term>
<termid>2</termid>
<termfrequency>0</termfrequency>
</term>
<term>
<termid>3</termid>
<termfrequency>0</termfrequency>
</term>
<term>
<termid>4</termid>
<termfrequency>0</termfrequency>
</term>
</stream>
<stream>
<streamid>2</streamid>
<length>0</length>
<uniquelength>0</uniquelength>
<term>
<termid>1</termid>
<termfrequency>0</termfrequency>
</term>
<term>
<termid>2</termid>
<termfrequency>0</termfrequency>
</term>
<term>
<termid>3</termid>
<termfrequency>0</termfrequency>
</term>
<term>
<termid>4</termid>
<termfrequency>0</termfrequency>
</term>
</stream>
<stream>
<streamid>3</streamid>
<length>4</length>
<uniquelength>4</uniquelength>
<term>
<termid>1</termid>
<termfrequency>0</termfrequency>
</term>
<term>
<termid>2</termid>
<termfrequency>0</termfrequency>
</term>
<term>
<termid>3</termid>
<termfrequency>0</termfrequency>
</term>
<term>
<termid>4</termid>
<termfrequency>0</termfrequency>
</term>
</stream>
</doc>
<doc>
<docid>87324</docid>
<label>0</label>
<stream>
<streamid>1</streamid>
<length>5</length>
<uniquelength>5</uniquelength>
<term>
<termid>1</termid>
<termfrequency>0</termfrequency>
</term>
<term>
<termid>2</termid>
<termfrequency>0</termfrequency>
</term>
<term>
<termid>3</termid>
<termfrequency>0</termfrequency>
</term>
<term>
<termid>4</termid>
<termfrequency>0</termfrequency>
</term>
</stream>
<stream>
<streamid>2</streamid>
<length>0</length>
<uniquelength>0</uniquelength>
<term>
<termid>1</termid>
<termfrequency>0</termfrequency>
</term>
<term>
<termid>2</termid>
<termfrequency>0</termfrequency>
</term>
<term>
<termid>3</termid>
<termfrequency>0</termfrequency>
</term>
<term>
<termid>4</termid>
<termfrequency>0</termfrequency>
</term>
</stream>
<stream>
<streamid>3</streamid>
<length>5</length>
<uniquelength>5</uniquelength>
<term>
<termid>1</termid>
<termfrequency>0</termfrequency>
</term>
<term>
<termid>2</termid>
<termfrequency>0</termfrequency>
</term>
<term>
<termid>3</termid>
<termfrequency>0</termfrequency>
</term>
<term>
<termid>4</termid>
<termfrequency>0</termfrequency>
</term>
</stream>
</doc>
<doc>
<docid>89247</docid>
<label>0</label>
<stream>
<streamid>1</streamid>
<length>3</length>
<uniquelength>3</uniquelength>
<term>
<termid>1</termid>
<termfrequency>0</termfrequency>
</term>
<term>
<termid>2</termid>
<termfrequency>0</termfrequency>
</term>
<term>
<termid>3</termid>
<termfrequency>0</termfrequency>
</term>
<term>
<termid>4</termid>
<termfrequency>0</termfrequency>
</term>
</stream>
<stream>
<streamid>2</streamid>
<length>0</length>
<uniquelength>0</uniquelength>
<term>
<termid>1</termid>
<termfrequency>0</termfrequency>
</term>
<term>
<termid>2</termid>
<termfrequency>0</termfrequency>
</term>
<term>
<termid>3</termid>
<termfrequency>0</termfrequency>
</term>
<term>
<termid>4</termid>
<termfrequency>0</termfrequency>
</term>
</stream>
<stream>
<streamid>3</streamid>
<length>3</length>
<uniquelength>3</uniquelength>
<term>
<termid>1</termid>
<termfrequency>0</termfrequency>
</term>
<term>
<termid>2</termid>
<termfrequency>0</termfrequency>
</term>
<term>
<termid>3</termid>
<termfrequency>0</termfrequency>
</term>
<term>
<termid>4</termid>
<termfrequency>0</termfrequency>
</term>
</stream>
</doc>
<doc>
<docid>102531</docid>
<label>0</label>
<stream>
<streamid>1</streamid>
<length>7</length>
<uniquelength>7</uniquelength>
<term>
<termid>1</termid>
<termfrequency>0</termfrequency>
</term>
<term>
<termid>2</termid>
<termfrequency>0</termfrequency>
</term>
<term>
<termid>3</termid>
<termfrequency>0</termfrequency>
</term>
<term>
<termid>4</termid>
<termfrequency>0</termfrequency>
</term>
</stream>
<stream>
<streamid>2</streamid>
<length>53</length>
<uniquelength>39</uniquelength>
<term>
<termid>1</termid>
<termfrequency>0</termfrequency>
</term>
<term>
<termid>2</termid>
<termfrequency>0</termfrequency>
</term>
<term>
<termid>3</termid>
<termfrequency>0</termfrequency>
</term>
<term>
<termid>4</termid>
<termfrequency>0</termfrequency>
</term>
</stream>
<stream>
<streamid>3</streamid>
<length>60</length>
<uniquelength>40</uniquelength>
<term>
<termid>1</termid>
<termfrequency>0</termfrequency>
</term>
<term>
<termid>2</termid>
<termfrequency>0</termfrequency>
</term>
<term>
<termid>3</termid>
<termfrequency>0</termfrequency>
</term>
<term>
<termid>4</termid>
<termfrequency>0</termfrequency>
</term>
</stream>
</doc>
<doc>
<docid>179393</docid>
<label>0</label>
<stream>
<streamid>1</streamid>
<length>3</length>
<uniquelength>3</uniquelength>
<term>
<termid>1</termid>
<termfrequency>0</termfrequency>
</term>
<term>
<termid>2</termid>
<termfrequency>0</termfrequency>
</term>
<term>
<termid>3</termid>
<termfrequency>0</termfrequency>
</term>
<term>
<termid>4</termid>
<termfrequency>0</termfrequency>
</term>
</stream>
<stream>
<streamid>2</streamid>
<length>0</length>
<uniquelength>0</uniquelength>
<term>
<termid>1</termid>
<termfrequency>0</termfrequency>
</term>
<term>
<termid>2</termid>
<termfrequency>0</termfrequency>
</term>
<term>
<termid>3</termid>
<termfrequency>0</termfrequency>
</term>
<term>
<termid>4</termid>
<termfrequency>0</termfrequency>
</term>
</stream>
<stream>
<streamid>3</streamid>
<length>3</length>
<uniquelength>3</uniquelength>
<term>
<termid>1</termid>
<termfrequency>0</termfrequency>
</term>
<term>
<termid>2</termid>
<termfrequency>0</termfrequency>
</term>
<term>
<termid>3</termid>
<termfrequency>0</termfrequency>
</term>
<term>
<termid>4</termid>
<termfrequency>0</termfrequency>
</term>
</stream>
</doc>
<doc>
<docid>194883</docid>
<label>0</label>
<stream>
<streamid>1</streamid>
<length>7</length>
<uniquelength>7</uniquelength>
<term>
<termid>1</termid>
<termfrequency>0</termfrequency>
</term>
<term>
<termid>2</termid>
<termfrequency>0</termfrequency>
</term>
<term>
<termid>3</termid>
<termfrequency>0</termfrequency>
</term>
<term>
<termid>4</termid>
<termfrequency>0</termfrequency>
</term>
</stream>
<stream>
<streamid>2</streamid>
<length>74</length>
<uniquelength>56</uniquelength>
<term>
<termid>1</termid>
<termfrequency>0</termfrequency>
</term>
<term>
<termid>2</termid>
<termfrequency>0</termfrequency>
</term>
<term>
<termid>3</termid>
<termfrequency>0</termfrequency>
</term>
<term>
<termid>4</termid>
<termfrequency>0</termfrequency>
</term>
</stream>
<stream>
<streamid>3</streamid>
<length>81</length>
<uniquelength>58</uniquelength>
<term>
<termid>1</termid>
<termfrequency>0</termfrequency>
</term>
<term>
<termid>2</termid>
<termfrequency>0</termfrequency>
</term>
<term>
<termid>3</termid>
<termfrequency>0</termfrequency>
</term>
<term>
<termid>4</termid>
<termfrequency>0</termfrequency>
</term>
</stream>
</doc>
<doc>
<docid>138305</docid>
<label>0</label>
<stream>
<streamid>1</streamid>
<length>5</length>
<uniquelength>5</uniquelength>
<term>
<termid>1</termid>
<termfrequency>0</termfrequency>
</term>
<term>
<termid>2</termid>
<termfrequency>0</termfrequency>
</term>
<term>
<termid>3</termid>
<termfrequency>0</termfrequency>
</term>
<term>
<termid>4</termid>
<termfrequency>0</termfrequency>
</term>
</stream>
<stream>
<streamid>2</streamid>
<length>48</length>
<uniquelength>41</uniquelength>
<term>
<termid>1</termid>
<termfrequency>0</termfrequency>
</term>
<term>
<termid>2</termid>
<termfrequency>0</termfrequency>
</term>
<term>
<termid>3</termid>
<termfrequency>0</termfrequency>
</term>
<term>
<termid>4</termid>
<termfrequency>0</termfrequency>
</term>
</stream>
<stream>
<streamid>3</streamid>
<length>53</length>
<uniquelength>43</uniquelength>
<term>
<termid>1</termid>
<termfrequency>0</termfrequency>
</term>
<term>
<termid>2</termid>
<termfrequency>0</termfrequency>
</term>
<term>
<termid>3</termid>
<termfrequency>0</termfrequency>
</term>
<term>
<termid>4</termid>
<termfrequency>0</termfrequency>
</term>
</stream>
</doc>
<doc>
<docid>138940</docid>
<label>1</label>
<stream>
<streamid>1</streamid>
<length>2</length>
<uniquelength>2</uniquelength>
<term>
<termid>1</termid>
<termfrequency>0</termfrequency>
</term>
<term>
<termid>2</termid>
<termfrequency>0</termfrequency>
</term>
<term>
<termid>3</termid>
<termfrequency>0</termfrequency>
</term>
<term>
<termid>4</termid>
<termfrequency>0</termfrequency>
</term>
</stream>
<stream>
<streamid>2</streamid>
<length>0</length>
<uniquelength>0</uniquelength>
<term>
<termid>1</termid>
<termfrequency>0</termfrequency>
</term>
<term>
<termid>2</termid>
<termfrequency>0</termfrequency>
</term>
<term>
<termid>3</termid>
<termfrequency>0</termfrequency>
</term>
<term>
<termid>4</termid>
<termfrequency>0</termfrequency>
</term>
</stream>
<stream>
<streamid>3</streamid>
<length>2</length>
<uniquelength>2</uniquelength>
<term>
<termid>1</termid>
<termfrequency>0</termfrequency>
</term>
<term>
<termid>2</termid>
<termfrequency>0</termfrequency>
</term>
<term>
<termid>3</termid>
<termfrequency>0</termfrequency>
</term>
<term>
<termid>4</termid>
<termfrequency>0</termfrequency>
</term>
</stream>
</doc>
<doc>
<docid>199944</docid>
<label>1</label>
<stream>
<streamid>1</streamid>
<length>1</length>
<uniquelength>1</uniquelength>
<term>
<termid>1</termid>
<termfrequency>0</termfrequency>
</term>
<term>
<termid>2</termid>
<termfrequency>0</termfrequency>
</term>
<term>
<termid>3</termid>
<termfrequency>0</termfrequency>
</term>
<term>
<termid>4</termid>
<termfrequency>0</termfrequency>
</term>
</stream>
<stream>
<streamid>2</streamid>
<length>0</length>
<uniquelength>0</uniquelength>
<term>
<termid>1</termid>
<termfrequency>0</termfrequency>
</term>
<term>
<termid>2</termid>
<termfrequency>0</termfrequency>
</term>
<term>
<termid>3</termid>
<termfrequency>0</termfrequency>
</term>
<term>
<termid>4</termid>
<termfrequency>0</termfrequency>
</term>
</stream>
<stream>
<streamid>3</streamid>
<length>1</length>
<uniquelength>1</uniquelength>
<term>
<termid>1</termid>
<termfrequency>0</termfrequency>
</term>
<term>
<termid>2</termid>
<termfrequency>0</termfrequency>
</term>
<term>
<termid>3</termid>
<termfrequency>0</termfrequency>
</term>
<term>
<termid>4</termid>
<termfrequency>0</termfrequency>
</term>
</stream>
</doc>
<doc>
<docid>161659</docid>
<label>0</label>
<stream>
<streamid>1</streamid>
<length>5</length>
<uniquelength>5</uniquelength>
<term>
<termid>1</termid>
<termfrequency>0</termfrequency>
</term>
<term>
<termid>2</termid>
<termfrequency>0</termfrequency>
</term>
<term>
<termid>3</termid>
<termfrequency>0</termfrequency>
</term>
<term>
<termid>4</termid>
<termfrequency>0</termfrequency>
</term>
</stream>
<stream>
<streamid>2</streamid>
<length>0</length>
<uniquelength>0</uniquelength>
<term>
<termid>1</termid>
<termfrequency>0</termfrequency>
</term>
<term>
<termid>2</termid>
<termfrequency>0</termfrequency>
</term>
<term>
<termid>3</termid>
<termfrequency>0</termfrequency>
</term>
<term>
<termid>4</termid>
<termfrequency>0</termfrequency>
</term>
</stream>
<stream>
<streamid>3</streamid>
<length>5</length>
<uniquelength>5</uniquelength>
<term>
<termid>1</termid>
<termfrequency>0</termfrequency>
</term>
<term>
<termid>2</termid>
<termfrequency>0</termfrequency>
</term>
<term>
<termid>3</termid>
<termfrequency>0</termfrequency>
</term>
<term>
<termid>4</termid>
<termfrequency>0</termfrequency>
</term>
</stream>
</doc>
<doc>
<docid>19046</docid>
<label>0</label>
<stream>
<streamid>1</streamid>
<length>22</length>
<uniquelength>22</uniquelength>
<term>
<termid>1</termid>
<termfrequency>0</termfrequency>
</term>
<term>
<termid>2</termid>
<termfrequency>0</termfrequency>
</term>
<term>
<termid>3</termid>
<termfrequency>0</termfrequency>
</term>
<term>
<termid>4</termid>
<termfrequency>0</termfrequency>
</term>
</stream>
<stream>
<streamid>2</streamid>
<length>117</length>
<uniquelength>58</uniquelength>
<term>
<termid>1</termid>
<termfrequency>0</termfrequency>
</term>
<term>
<termid>2</termid>
<termfrequency>0</termfrequency>
</term>
<term>
<termid>3</termid>
<termfrequency>0</termfrequency>
</term>
<term>
<termid>4</termid>
<termfrequency>0</termfrequency>
</term>
</stream>
<stream>
<streamid>3</streamid>
<length>139</length>
<uniquelength>70</uniquelength>
<term>
<termid>1</termid>
<termfrequency>0</termfrequency>
</term>
<term>
<termid>2</termid>
<termfrequency>0</termfrequency>
</term>
<term>
<termid>3</termid>
<termfrequency>0</termfrequency>
</term>
<term>
<termid>4</termid>
<termfrequency>0</termfrequency>
</term>
</stream>
</doc>
<doc>
<docid>164978</docid>
<label>0</label>
<stream>
<streamid>1</streamid>
<length>5</length>
<uniquelength>5</uniquelength>
<term>
<termid>1</termid>
<termfrequency>0</termfrequency>
</term>
<term>
<termid>2</termid>
<termfrequency>0</termfrequency>
</term>
<term>
<termid>3</termid>
<termfrequency>0</termfrequency>
</term>
<term>
<termid>4</termid>
<termfrequency>0</termfrequency>
</term>
</stream>
<stream>
<streamid>2</streamid>
<length>0</length>
<uniquelength>0</uniquelength>
<term>
<termid>1</termid>
<termfrequency>0</termfrequency>
</term>
<term>
<termid>2</termid>
<termfrequency>0</termfrequency>
</term>
<term>
<termid>3</termid>
<termfrequency>0</termfrequency>
</term>
<term>
<termid>4</termid>
<termfrequency>0</termfrequency>
</term>
</stream>
<stream>
<streamid>3</streamid>
<length>5</length>
<uniquelength>5</uniquelength>
<term>
<termid>1</termid>
<termfrequency>0</termfrequency>
</term>
<term>
<termid>2</termid>
<termfrequency>0</termfrequency>
</term>
<term>
<termid>3</termid>
<termfrequency>0</termfrequency>
</term>
<term>
<termid>4</termid>
<termfrequency>0</termfrequency>
</term>
</stream>
</doc>
<doc>
<docid>169652</docid>
<label>0</label>
<stream>
<streamid>1</streamid>
<length>7</length>
<uniquelength>7</uniquelength>
<term>
<termid>1</termid>
<termfrequency>0</termfrequency>
</term>
<term>
<termid>2</termid>
<termfrequency>0</termfrequency>
</term>
<term>
<termid>3</termid>
<termfrequency>0</termfrequency>
</term>
<term>
<termid>4</termid>
<termfrequency>0</termfrequency>
</term>
</stream>
<stream>
<streamid>2</streamid>
<length>52</length>
<uniquelength>39</uniquelength>
<term>
<termid>1</termid>
<termfrequency>0</termfrequency>
</term>
<term>
<termid>2</termid>
<termfrequency>0</termfrequency>
</term>
<term>
<termid>3</termid>
<termfrequency>0</termfrequency>
</term>
<term>
<termid>4</termid>
<termfrequency>0</termfrequency>
</term>
</stream>
<stream>
<streamid>3</streamid>
<length>59</length>
<uniquelength>39</uniquelength>
<term>
<termid>1</termid>
<termfrequency>0</termfrequency>
</term>
<term>
<termid>2</termid>
<termfrequency>0</termfrequency>
</term>
<term>
<termid>3</termid>
<termfrequency>0</termfrequency>
</term>
<term>
<termid>4</termid>
<termfrequency>0</termfrequency>
</term>
</stream>
</doc>
<doc>
<docid>170566</docid>
<label>0</label>
<stream>
<streamid>1</streamid>
<length>6</length>
<uniquelength>6</uniquelength>
<term>
<termid>1</termid>
<termfrequency>0</termfrequency>
</term>
<term>
<termid>2</termid>
<termfrequency>0</termfrequency>
</term>
<term>
<termid>3</termid>
<termfrequency>0</termfrequency>
</term>
<term>
<termid>4</termid>
<termfrequency>0</termfrequency>
</term>
</stream>
<stream>
<streamid>2</streamid>
<length>0</length>
<uniquelength>0</uniquelength>
<term>
<termid>1</termid>
<termfrequency>0</termfrequency>
</term>
<term>
<termid>2</termid>
<termfrequency>0</termfrequency>
</term>
<term>
<termid>3</termid>
<termfrequency>0</termfrequency>
</term>
<term>
<termid>4</termid>
<termfrequency>0</termfrequency>
</term>
</stream>
<stream>
<streamid>3</streamid>
<length>6</length>
<uniquelength>6</uniquelength>
<term>
<termid>1</termid>
<termfrequency>0</termfrequency>
</term>
<term>
<termid>2</termid>
<termfrequency>0</termfrequency>
</term>
<term>
<termid>3</termid>
<termfrequency>0</termfrequency>
</term>
<term>
<termid>4</termid>
<termfrequency>0</termfrequency>
</term>
</stream>
</doc>
<doc>
<docid>170785</docid>
<label>0</label>
<stream>
<streamid>1</streamid>
<length>5</length>
<uniquelength>5</uniquelength>
<term>
<termid>1</termid>
<termfrequency>0</termfrequency>
</term>
<term>
<termid>2</termid>
<termfrequency>0</termfrequency>
</term>
<term>
<termid>3</termid>
<termfrequency>0</termfrequency>
</term>
<term>
<termid>4</termid>
<termfrequency>0</termfrequency>
</term>
</stream>
<stream>
<streamid>2</streamid>
<length>0</length>
<uniquelength>0</uniquelength>
<term>
<termid>1</termid>
<termfrequency>0</termfrequency>
</term>
<term>
<termid>2</termid>
<termfrequency>0</termfrequency>
</term>
<term>
<termid>3</termid>
<termfrequency>0</termfrequency>
</term>
<term>
<termid>4</termid>
<termfrequency>0</termfrequency>
</term>
</stream>
<stream>
<streamid>3</streamid>
<length>5</length>
<uniquelength>5</uniquelength>
<term>
<termid>1</termid>
<termfrequency>0</termfrequency>
</term>
<term>
<termid>2</termid>
<termfrequency>0</termfrequency>
</term>
<term>
<termid>3</termid>
<termfrequency>0</termfrequency>
</term>
<term>
<termid>4</termid>
<termfrequency>0</termfrequency>
</term>
</stream>
</doc>
<doc>
<docid>20571</docid>
<label>0</label>
<stream>
<streamid>1</streamid>
<length>8</length>
<uniquelength>8</uniquelength>
<term>
<termid>1</termid>
<termfrequency>0</termfrequency>
</term>
<term>
<termid>2</termid>
<termfrequency>0</termfrequency>
</term>
<term>
<termid>3</termid>
<termfrequency>0</termfrequency>
</term>
<term>
<termid>4</termid>
<termfrequency>0</termfrequency>
</term>
</stream>
<stream>
<streamid>2</streamid>
<length>0</length>
<uniquelength>0</uniquelength>
<term>
<termid>1</termid>
<termfrequency>0</termfrequency>
</term>
<term>
<termid>2</termid>
<termfrequency>0</termfrequency>
</term>
<term>
<termid>3</termid>
<termfrequency>0</termfrequency>
</term>
<term>
<termid>4</termid>
<termfrequency>0</termfrequency>
</term>
</stream>
<stream>
<streamid>3</streamid>
<length>8</length>
<uniquelength>8</uniquelength>
<term>
<termid>1</termid>
<termfrequency>0</termfrequency>
</term>
<term>
<termid>2</termid>
<termfrequency>0</termfrequency>
</term>
<term>
<termid>3</termid>
<termfrequency>0</termfrequency>
</term>
<term>
<termid>4</termid>
<termfrequency>0</termfrequency>
</term>
</stream>
</doc>
<doc>
<docid>173021</docid>
<label>0</label>
<stream>
<streamid>1</streamid>
<length>9</length>
<uniquelength>9</uniquelength>
<term>
<termid>1</termid>
<termfrequency>0</termfrequency>
</term>
<term>
<termid>2</termid>
<termfrequency>0</termfrequency>
</term>
<term>
<termid>3</termid>
<termfrequency>0</termfrequency>
</term>
<term>
<termid>4</termid>
<termfrequency>0</termfrequency>
</term>
</stream>
<stream>
<streamid>2</streamid>
<length>57</length>
<uniquelength>44</uniquelength>
<term>
<termid>1</termid>
<termfrequency>0</termfrequency>
</term>
<term>
<termid>2</termid>
<termfrequency>0</termfrequency>
</term>
<term>
<termid>3</termid>
<termfrequency>0</termfrequency>
</term>
<term>
<termid>4</termid>
<termfrequency>0</termfrequency>
</term>
</stream>
<stream>
<streamid>3</streamid>
<length>66</length>
<uniquelength>44</uniquelength>
<term>
<termid>1</termid>
<termfrequency>0</termfrequency>
</term>
<term>
<termid>2</termid>
<termfrequency>0</termfrequency>
</term>
<term>
<termid>3</termid>
<termfrequency>0</termfrequency>
</term>
<term>
<termid>4</termid>
<termfrequency>0</termfrequency>
</term>
</stream>
</doc>
<doc>
<docid>173079</docid>
<label>0</label>
<stream>
<streamid>1</streamid>
<length>5</length>
<uniquelength>5</uniquelength>
<term>
<termid>1</termid>
<termfrequency>0</termfrequency>
</term>
<term>
<termid>2</termid>
<termfrequency>0</termfrequency>
</term>
<term>
<termid>3</termid>
<termfrequency>0</termfrequency>
</term>
<term>
<termid>4</termid>
<termfrequency>0</termfrequency>
</term>
</stream>
<stream>
<streamid>2</streamid>
<length>0</length>
<uniquelength>0</uniquelength>
<term>
<termid>1</termid>
<termfrequency>0</termfrequency>
</term>
<term>
<termid>2</termid>
<termfrequency>0</termfrequency>
</term>
<term>
<termid>3</termid>
<termfrequency>0</termfrequency>
</term>
<term>
<termid>4</termid>
<termfrequency>0</termfrequency>
</term>
</stream>
<stream>
<streamid>3</streamid>
<length>5</length>
<uniquelength>5</uniquelength>
<term>
<termid>1</termid>
<termfrequency>0</termfrequency>
</term>
<term>
<termid>2</termid>
<termfrequency>0</termfrequency>
</term>
<term>
<termid>3</termid>
<termfrequency>0</termfrequency>
</term>
<term>
<termid>4</termid>
<termfrequency>0</termfrequency>
</term>
</stream>
</doc>
<doc>
<docid>175209</docid>
<label>0</label>
<stream>
<streamid>1</streamid>
<length>6</length>
<uniquelength>6</uniquelength>
<term>
<termid>1</termid>
<termfrequency>0</termfrequency>
</term>
<term>
<termid>2</termid>
<termfrequency>0</termfrequency>
</term>
<term>
<termid>3</termid>
<termfrequency>0</termfrequency>
</term>
<term>
<termid>4</termid>
<termfrequency>0</termfrequency>
</term>
</stream>
<stream>
<streamid>2</streamid>
<length>0</length>
<uniquelength>0</uniquelength>
<term>
<termid>1</termid>
<termfrequency>0</termfrequency>
</term>
<term>
<termid>2</termid>
<termfrequency>0</termfrequency>
</term>
<term>
<termid>3</termid>
<termfrequency>0</termfrequency>
</term>
<term>
<termid>4</termid>
<termfrequency>0</termfrequency>
</term>
</stream>
<stream>
<streamid>3</streamid>
<length>6</length>
<uniquelength>6</uniquelength>
<term>
<termid>1</termid>
<termfrequency>0</termfrequency>
</term>
<term>
<termid>2</termid>
<termfrequency>0</termfrequency>
</term>
<term>
<termid>3</termid>
<termfrequency>0</termfrequency>
</term>
<term>
<termid>4</termid>
<termfrequency>0</termfrequency>
</term>
</stream>
</doc>
<doc>
<docid>178614</docid>
<label>0</label>
<stream>
<streamid>1</streamid>
<length>6</length>
<uniquelength>5</uniquelength>
<term>
<termid>1</termid>
<termfrequency>0</termfrequency>
</term>
<term>
<termid>2</termid>
<termfrequency>0</termfrequency>
</term>
<term>
<termid>3</termid>
<termfrequency>0</termfrequency>
</term>
<term>
<termid>4</termid>
<termfrequency>0</termfrequency>
</term>
</stream>
<stream>
<streamid>2</streamid>
<length>0</length>
<uniquelength>0</uniquelength>
<term>
<termid>1</termid>
<termfrequency>0</termfrequency>
</term>
<term>
<termid>2</termid>
<termfrequency>0</termfrequency>
</term>
<term>
<termid>3</termid>
<termfrequency>0</termfrequency>
</term>
<term>
<termid>4</termid>
<termfrequency>0</termfrequency>
</term>
</stream>
<stream>
<streamid>3</streamid>
<length>6</length>
<uniquelength>5</uniquelength>
<term>
<termid>1</termid>
<termfrequency>0</termfrequency>
</term>
<term>
<termid>2</termid>
<termfrequency>0</termfrequency>
</term>
<term>
<termid>3</termid>
<termfrequency>0</termfrequency>
</term>
<term>
<termid>4</termid>
<termfrequency>0</termfrequency>
</term>
</stream>
</doc>
<doc>
<docid>21781</docid>
<label>0</label>
<stream>
<streamid>1</streamid>
<length>13</length>
<uniquelength>12</uniquelength>
<term>
<termid>1</termid>
<termfrequency>0</termfrequency>
</term>
<term>
<termid>2</termid>
<termfrequency>0</termfrequency>
</term>
<term>
<termid>3</termid>
<termfrequency>0</termfrequency>
</term>
<term>
<termid>4</termid>
<termfrequency>0</termfrequency>
</term>
</stream>
<stream>
<streamid>2</streamid>
<length>61</length>
<uniquelength>55</uniquelength>
<term>
<termid>1</termid>
<termfrequency>0</termfrequency>
</term>
<term>
<termid>2</termid>
<termfrequency>0</termfrequency>
</term>
<term>
<termid>3</termid>
<termfrequency>0</termfrequency>
</term>
<term>
<termid>4</termid>
<termfrequency>0</termfrequency>
</term>
</stream>
<stream>
<streamid>3</streamid>
<length>74</length>
<uniquelength>62</uniquelength>
<term>
<termid>1</termid>
<termfrequency>0</termfrequency>
</term>
<term>
<termid>2</termid>
<termfrequency>0</termfrequency>
</term>
<term>
<termid>3</termid>
<termfrequency>0</termfrequency>
</term>
<term>
<termid>4</termid>
<termfrequency>0</termfrequency>
</term>
</stream>
</doc>
<doc>
<docid>126485</docid>
<label>0</label>
<stream>
<streamid>1</streamid>
<length>5</length>
<uniquelength>5</uniquelength>
<term>
<termid>1</termid>
<termfrequency>0</termfrequency>
</term>
<term>
<termid>2</termid>
<termfrequency>0</termfrequency>
</term>
<term>
<termid>3</termid>
<termfrequency>0</termfrequency>
</term>
<term>
<termid>4</termid>
<termfrequency>0</termfrequency>
</term>
</stream>
<stream>
<streamid>2</streamid>
<length>0</length>
<uniquelength>0</uniquelength>
<term>
<termid>1</termid>
<termfrequency>0</termfrequency>
</term>
<term>
<termid>2</termid>
<termfrequency>0</termfrequency>
</term>
<term>
<termid>3</termid>
<termfrequency>0</termfrequency>
</term>
<term>
<termid>4</termid>
<termfrequency>0</termfrequency>
</term>
</stream>
<stream>
<streamid>3</streamid>
<length>5</length>
<uniquelength>5</uniquelength>
<term>
<termid>1</termid>
<termfrequency>0</termfrequency>
</term>
<term>
<termid>2</termid>
<termfrequency>0</termfrequency>
</term>
<term>
<termid>3</termid>
<termfrequency>0</termfrequency>
</term>
<term>
<termid>4</termid>
<termfrequency>0</termfrequency>
</term>
</stream>
</doc>
<doc>
<docid>131232</docid>
<label>0</label>
<stream>
<streamid>1</streamid>
<length>3</length>
<uniquelength>3</uniquelength>
<term>
<termid>1</termid>
<termfrequency>0</termfrequency>
</term>
<term>
<termid>2</termid>
<termfrequency>0</termfrequency>
</term>
<term>
<termid>3</termid>
<termfrequency>0</termfrequency>
</term>
<term>
<termid>4</termid>
<termfrequency>0</termfrequency>
</term>
</stream>
<stream>
<streamid>2</streamid>
<length>0</length>
<uniquelength>0</uniquelength>
<term>
<termid>1</termid>
<termfrequency>0</termfrequency>
</term>
<term>
<termid>2</termid>
<termfrequency>0</termfrequency>
</term>
<term>
<termid>3</termid>
<termfrequency>0</termfrequency>
</term>
<term>
<termid>4</termid>
<termfrequency>0</termfrequency>
</term>
</stream>
<stream>
<streamid>3</streamid>
<length>3</length>
<uniquelength>3</uniquelength>
<term>
<termid>1</termid>
<termfrequency>0</termfrequency>
</term>
<term>
<termid>2</termid>
<termfrequency>0</termfrequency>
</term>
<term>
<termid>3</termid>
<termfrequency>0</termfrequency>
</term>
<term>
<termid>4</termid>
<termfrequency>0</termfrequency>
</term>
</stream>
</doc>
<doc>
<docid>131260</docid>
<label>0</label>
<stream>
<streamid>1</streamid>
<length>4</length>
<uniquelength>4</uniquelength>
<term>
<termid>1</termid>
<termfrequency>0</termfrequency>
</term>
<term>
<termid>2</termid>
<termfrequency>0</termfrequency>
</term>
<term>
<termid>3</termid>
<termfrequency>0</termfrequency>
</term>
<term>
<termid>4</termid>
<termfrequency>0</termfrequency>
</term>
</stream>
<stream>
<streamid>2</streamid>
<length>0</length>
<uniquelength>0</uniquelength>
<term>
<termid>1</termid>
<termfrequency>0</termfrequency>
</term>
<term>
<termid>2</termid>
<termfrequency>0</termfrequency>
</term>
<term>
<termid>3</termid>
<termfrequency>0</termfrequency>
</term>
<term>
<termid>4</termid>
<termfrequency>0</termfrequency>
</term>
</stream>
<stream>
<streamid>3</streamid>
<length>4</length>
<uniquelength>4</uniquelength>
<term>
<termid>1</termid>
<termfrequency>0</termfrequency>
</term>
<term>
<termid>2</termid>
<termfrequency>0</termfrequency>
</term>
<term>
<termid>3</termid>
<termfrequency>0</termfrequency>
</term>
<term>
<termid>4</termid>
<termfrequency>0</termfrequency>
</term>
</stream>
</doc>
<doc>
<docid>137376</docid>
<label>0</label>
<stream>
<streamid>1</streamid>
<length>4</length>
<uniquelength>4</uniquelength>
<term>
<termid>1</termid>
<termfrequency>0</termfrequency>
</term>
<term>
<termid>2</termid>
<termfrequency>0</termfrequency>
</term>
<term>
<termid>3</termid>
<termfrequency>0</termfrequency>
</term>
<term>
<termid>4</termid>
<termfrequency>0</termfrequency>
</term>
</stream>
<stream>
<streamid>2</streamid>
<length>0</length>
<uniquelength>0</uniquelength>
<term>
<termid>1</termid>
<termfrequency>0</termfrequency>
</term>
<term>
<termid>2</termid>
<termfrequency>0</termfrequency>
</term>
<term>
<termid>3</termid>
<termfrequency>0</termfrequency>
</term>
<term>
<termid>4</termid>
<termfrequency>0</termfrequency>
</term>
</stream>
<stream>
<streamid>3</streamid>
<length>4</length>
<uniquelength>4</uniquelength>
<term>
<termid>1</termid>
<termfrequency>0</termfrequency>
</term>
<term>
<termid>2</termid>
<termfrequency>0</termfrequency>
</term>
<term>
<termid>3</termid>
<termfrequency>0</termfrequency>
</term>
<term>
<termid>4</termid>
<termfrequency>0</termfrequency>
</term>
</stream>
</doc>
<doc>
<docid>133919</docid>
<label>0</label>
<stream>
<streamid>1</streamid>
<length>6</length>
<uniquelength>6</uniquelength>
<term>
<termid>1</termid>
<termfrequency>0</termfrequency>
</term>
<term>
<termid>2</termid>
<termfrequency>0</termfrequency>
</term>
<term>
<termid>3</termid>
<termfrequency>0</termfrequency>
</term>
<term>
<termid>4</termid>
<termfrequency>0</termfrequency>
</term>
</stream>
<stream>
<streamid>2</streamid>
<length>62</length>
<uniquelength>41</uniquelength>
<term>
<termid>1</termid>
<termfrequency>0</termfrequency>
</term>
<term>
<termid>2</termid>
<termfrequency>0</termfrequency>
</term>
<term>
<termid>3</termid>
<termfrequency>0</termfrequency>
</term>
<term>
<termid>4</termid>
<termfrequency>0</termfrequency>
</term>
</stream>
<stream>
<streamid>3</streamid>
<length>68</length>
<uniquelength>41</uniquelength>
<term>
<termid>1</termid>
<termfrequency>0</termfrequency>
</term>
<term>
<termid>2</termid>
<termfrequency>0</termfrequency>
</term>
<term>
<termid>3</termid>
<termfrequency>0</termfrequency>
</term>
<term>
<termid>4</termid>
<termfrequency>0</termfrequency>
</term>
</stream>
</doc>
<doc>
<docid>265001</docid>
<label>0</label>
<stream>
<streamid>1</streamid>
<length>5</length>
<uniquelength>5</uniquelength>
<term>
<termid>1</termid>
<termfrequency>0</termfrequency>
</term>
<term>
<termid>2</termid>
<termfrequency>0</termfrequency>
</term>
<term>
<termid>3</termid>
<termfrequency>0</termfrequency>
</term>
<term>
<termid>4</termid>
<termfrequency>0</termfrequency>
</term>
</stream>
<stream>
<streamid>2</streamid>
<length>0</length>
<uniquelength>0</uniquelength>
<term>
<termid>1</termid>
<termfrequency>0</termfrequency>
</term>
<term>
<termid>2</termid>
<termfrequency>0</termfrequency>
</term>
<term>
<termid>3</termid>
<termfrequency>0</termfrequency>
</term>
<term>
<termid>4</termid>
<termfrequency>0</termfrequency>
</term>
</stream>
<stream>
<streamid>3</streamid>
<length>5</length>
<uniquelength>5</uniquelength>
<term>
<termid>1</termid>
<termfrequency>0</termfrequency>
</term>
<term>
<termid>2</termid>
<termfrequency>0</termfrequency>
</term>
<term>
<termid>3</termid>
<termfrequency>0</termfrequency>
</term>
<term>
<termid>4</termid>
<termfrequency>0</termfrequency>
</term>
</stream>
</doc>
<doc>
<docid>202193</docid>
<label>0</label>
<stream>
<streamid>1</streamid>
<length>3</length>
<uniquelength>3</uniquelength>
<term>
<termid>1</termid>
<termfrequency>0</termfrequency>
</term>
<term>
<termid>2</termid>
<termfrequency>0</termfrequency>
</term>
<term>
<termid>3</termid>
<termfrequency>0</termfrequency>
</term>
<term>
<termid>4</termid>
<termfrequency>0</termfrequency>
</term>
</stream>
<stream>
<streamid>2</streamid>
<length>0</length>
<uniquelength>0</uniquelength>
<term>
<termid>1</termid>
<termfrequency>0</termfrequency>
</term>
<term>
<termid>2</termid>
<termfrequency>0</termfrequency>
</term>
<term>
<termid>3</termid>
<termfrequency>0</termfrequency>
</term>
<term>
<termid>4</termid>
<termfrequency>0</termfrequency>
</term>
</stream>
<stream>
<streamid>3</streamid>
<length>3</length>
<uniquelength>3</uniquelength>
<term>
<termid>1</termid>
<termfrequency>0</termfrequency>
</term>
<term>
<termid>2</termid>
<termfrequency>0</termfrequency>
</term>
<term>
<termid>3</termid>
<termfrequency>0</termfrequency>
</term>
<term>
<termid>4</termid>
<termfrequency>0</termfrequency>
</term>
</stream>
</doc>
<doc>
<docid>202323</docid>
<label>0</label>
<stream>
<streamid>1</streamid>
<length>4</length>
<uniquelength>4</uniquelength>
<term>
<termid>1</termid>
<termfrequency>0</termfrequency>
</term>
<term>
<termid>2</termid>
<termfrequency>0</termfrequency>
</term>
<term>
<termid>3</termid>
<termfrequency>0</termfrequency>
</term>
<term>
<termid>4</termid>
<termfrequency>0</termfrequency>
</term>
</stream>
<stream>
<streamid>2</streamid>
<length>0</length>
<uniquelength>0</uniquelength>
<term>
<termid>1</termid>
<termfrequency>0</termfrequency>
</term>
<term>
<termid>2</termid>
<termfrequency>0</termfrequency>
</term>
<term>
<termid>3</termid>
<termfrequency>0</termfrequency>
</term>
<term>
<termid>4</termid>
<termfrequency>0</termfrequency>
</term>
</stream>
<stream>
<streamid>3</streamid>
<length>4</length>
<uniquelength>4</uniquelength>
<term>
<termid>1</termid>
<termfrequency>0</termfrequency>
</term>
<term>
<termid>2</termid>
<termfrequency>0</termfrequency>
</term>
<term>
<termid>3</termid>
<termfrequency>0</termfrequency>
</term>
<term>
<termid>4</termid>
<termfrequency>0</termfrequency>
</term>
</stream>
</doc>
<doc>
<docid>205814</docid>
<label>0</label>
<stream>
<streamid>1</streamid>
<length>3</length>
<uniquelength>3</uniquelength>
<term>
<termid>1</termid>
<termfrequency>0</termfrequency>
</term>
<term>
<termid>2</termid>
<termfrequency>0</termfrequency>
</term>
<term>
<termid>3</termid>
<termfrequency>0</termfrequency>
</term>
<term>
<termid>4</termid>
<termfrequency>0</termfrequency>
</term>
</stream>
<stream>
<streamid>2</streamid>
<length>0</length>
<uniquelength>0</uniquelength>
<term>
<termid>1</termid>
<termfrequency>0</termfrequency>
</term>
<term>
<termid>2</termid>
<termfrequency>0</termfrequency>
</term>
<term>
<termid>3</termid>
<termfrequency>0</termfrequency>
</term>
<term>
<termid>4</termid>
<termfrequency>0</termfrequency>
</term>
</stream>
<stream>
<streamid>3</streamid>
<length>3</length>
<uniquelength>3</uniquelength>
<term>
<termid>1</termid>
<termfrequency>0</termfrequency>
</term>
<term>
<termid>2</termid>
<termfrequency>0</termfrequency>
</term>
<term>
<termid>3</termid>
<termfrequency>0</termfrequency>
</term>
<term>
<termid>4</termid>
<termfrequency>0</termfrequency>
</term>
</stream>
</doc>
<doc>
<docid>23538</docid>
<label>0</label>
<stream>
<streamid>1</streamid>
<length>9</length>
<uniquelength>9</uniquelength>
<term>
<termid>1</termid>
<termfrequency>0</termfrequency>
</term>
<term>
<termid>2</termid>
<termfrequency>0</termfrequency>
</term>
<term>
<termid>3</termid>
<termfrequency>0</termfrequency>
</term>
<term>
<termid>4</termid>
<termfrequency>0</termfrequency>
</term>
</stream>
<stream>
<streamid>2</streamid>
<length>135</length>
<uniquelength>92</uniquelength>
<term>
<termid>1</termid>
<termfrequency>0</termfrequency>
</term>
<term>
<termid>2</termid>
<termfrequency>0</termfrequency>
</term>
<term>
<termid>3</termid>
<termfrequency>0</termfrequency>
</term>
<term>
<termid>4</termid>
<termfrequency>0</termfrequency>
</term>
</stream>
<stream>
<streamid>3</streamid>
<length>144</length>
<uniquelength>94</uniquelength>
<term>
<termid>1</termid>
<termfrequency>0</termfrequency>
</term>
<term>
<termid>2</termid>
<termfrequency>0</termfrequency>
</term>
<term>
<termid>3</termid>
<termfrequency>0</termfrequency>
</term>
<term>
<termid>4</termid>
<termfrequency>0</termfrequency>
</term>
</stream>
</doc>
<doc>
<docid>211043</docid>
<label>1</label>
<stream>
<streamid>1</streamid>
<length>10</length>
<uniquelength>10</uniquelength>
<term>
<termid>1</termid>
<termfrequency>0</termfrequency>
</term>
<term>
<termid>2</termid>
<termfrequency>0</termfrequency>
</term>
<term>
<termid>3</termid>
<termfrequency>0</termfrequency>
</term>
<term>
<termid>4</termid>
<termfrequency>0</termfrequency>
</term>
</stream>
<stream>
<streamid>2</streamid>
<length>60</length>
<uniquelength>50</uniquelength>
<term>
<termid>1</termid>
<termfrequency>0</termfrequency>
</term>
<term>
<termid>2</termid>
<termfrequency>0</termfrequency>
</term>
<term>
<termid>3</termid>
<termfrequency>0</termfrequency>
</term>
<term>
<termid>4</termid>
<termfrequency>0</termfrequency>
</term>
</stream>
<stream>
<streamid>3</streamid>
<length>70</length>
<uniquelength>56</uniquelength>
<term>
<termid>1</termid>
<termfrequency>0</termfrequency>
</term>
<term>
<termid>2</termid>
<termfrequency>0</termfrequency>
</term>
<term>
<termid>3</termid>
<termfrequency>0</termfrequency>
</term>
<term>
<termid>4</termid>
<termfrequency>0</termfrequency>
</term>
</stream>
</doc>
<doc>
<docid>214417</docid>
<label>0</label>
<stream>
<streamid>1</streamid>
<length>8</length>
<uniquelength>8</uniquelength>
<term>
<termid>1</termid>
<termfrequency>0</termfrequency>
</term>
<term>
<termid>2</termid>
<termfrequency>0</termfrequency>
</term>
<term>
<termid>3</termid>
<termfrequency>0</termfrequency>
</term>
<term>
<termid>4</termid>
<termfrequency>0</termfrequency>
</term>
</stream>
<stream>
<streamid>2</streamid>
<length>0</length>
<uniquelength>0</uniquelength>
<term>
<termid>1</termid>
<termfrequency>0</termfrequency>
</term>
<term>
<termid>2</termid>
<termfrequency>0</termfrequency>
</term>
<term>
<termid>3</termid>
<termfrequency>0</termfrequency>
</term>
<term>
<termid>4</termid>
<termfrequency>0</termfrequency>
</term>
</stream>
<stream>
<streamid>3</streamid>
<length>8</length>
<uniquelength>8</uniquelength>
<term>
<termid>1</termid>
<termfrequency>0</termfrequency>
</term>
<term>
<termid>2</termid>
<termfrequency>0</termfrequency>
</term>
<term>
<termid>3</termid>
<termfrequency>0</termfrequency>
</term>
<term>
<termid>4</termid>
<termfrequency>0</termfrequency>
</term>
</stream>
</doc>
<doc>
<docid>55782</docid>
<label>0</label>
<stream>
<streamid>1</streamid>
<length>5</length>
<uniquelength>5</uniquelength>
<term>
<termid>1</termid>
<termfrequency>0</termfrequency>
</term>
<term>
<termid>2</termid>
<termfrequency>0</termfrequency>
</term>
<term>
<termid>3</termid>
<termfrequency>0</termfrequency>
</term>
<term>
<termid>4</termid>
<termfrequency>0</termfrequency>
</term>
</stream>
<stream>
<streamid>2</streamid>
<length>82</length>
<uniquelength>63</uniquelength>
<term>
<termid>1</termid>
<termfrequency>0</termfrequency>
</term>
<term>
<termid>2</termid>
<termfrequency>0</termfrequency>
</term>
<term>
<termid>3</termid>
<termfrequency>0</termfrequency>
</term>
<term>
<termid>4</termid>
<termfrequency>0</termfrequency>
</term>
</stream>
<stream>
<streamid>3</streamid>
<length>87</length>
<uniquelength>65</uniquelength>
<term>
<termid>1</termid>
<termfrequency>0</termfrequency>
</term>
<term>
<termid>2</termid>
<termfrequency>0</termfrequency>
</term>
<term>
<termid>3</termid>
<termfrequency>0</termfrequency>
</term>
<term>
<termid>4</termid>
<termfrequency>0</termfrequency>
</term>
</stream>
</doc>
<doc>
<docid>230593</docid>
<label>0</label>
<stream>
<streamid>1</streamid>
<length>4</length>
<uniquelength>4</uniquelength>
<term>
<termid>1</termid>
<termfrequency>0</termfrequency>
</term>
<term>
<termid>2</termid>
<termfrequency>0</termfrequency>
</term>
<term>
<termid>3</termid>
<termfrequency>0</termfrequency>
</term>
<term>
<termid>4</termid>
<termfrequency>0</termfrequency>
</term>
</stream>
<stream>
<streamid>2</streamid>
<length>0</length>
<uniquelength>0</uniquelength>
<term>
<termid>1</termid>
<termfrequency>0</termfrequency>
</term>
<term>
<termid>2</termid>
<termfrequency>0</termfrequency>
</term>
<term>
<termid>3</termid>
<termfrequency>0</termfrequency>
</term>
<term>
<termid>4</termid>
<termfrequency>0</termfrequency>
</term>
</stream>
<stream>
<streamid>3</streamid>
<length>4</length>
<uniquelength>4</uniquelength>
<term>
<termid>1</termid>
<termfrequency>0</termfrequency>
</term>
<term>
<termid>2</termid>
<termfrequency>0</termfrequency>
</term>
<term>
<termid>3</termid>
<termfrequency>0</termfrequency>
</term>
<term>
<termid>4</termid>
<termfrequency>0</termfrequency>
</term>
</stream>
</doc>
<doc>
<docid>40648</docid>
<label>0</label>
<stream>
<streamid>1</streamid>
<length>10</length>
<uniquelength>8</uniquelength>
<term>
<termid>1</termid>
<termfrequency>0</termfrequency>
</term>
<term>
<termid>2</termid>
<termfrequency>0</termfrequency>
</term>
<term>
<termid>3</termid>
<termfrequency>0</termfrequency>
</term>
<term>
<termid>4</termid>
<termfrequency>0</termfrequency>
</term>
</stream>
<stream>
<streamid>2</streamid>
<length>47</length>
<uniquelength>38</uniquelength>
<term>
<termid>1</termid>
<termfrequency>0</termfrequency>
</term>
<term>
<termid>2</termid>
<termfrequency>0</termfrequency>
</term>
<term>
<termid>3</termid>
<termfrequency>0</termfrequency>
</term>
<term>
<termid>4</termid>
<termfrequency>0</termfrequency>
</term>
</stream>
<stream>
<streamid>3</streamid>
<length>57</length>
<uniquelength>39</uniquelength>
<term>
<termid>1</termid>
<termfrequency>0</termfrequency>
</term>
<term>
<termid>2</termid>
<termfrequency>0</termfrequency>
</term>
<term>
<termid>3</termid>
<termfrequency>0</termfrequency>
</term>
<term>
<termid>4</termid>
<termfrequency>0</termfrequency>
</term>
</stream>
</doc>
<doc>
<docid>259348</docid>
<label>0</label>
<stream>
<streamid>1</streamid>
<length>2</length>
<uniquelength>2</uniquelength>
<term>
<termid>1</termid>
<termfrequency>0</termfrequency>
</term>
<term>
<termid>2</termid>
<termfrequency>0</termfrequency>
</term>
<term>
<termid>3</termid>
<termfrequency>0</termfrequency>
</term>
<term>
<termid>4</termid>
<termfrequency>0</termfrequency>
</term>
</stream>
<stream>
<streamid>2</streamid>
<length>56</length>
<uniquelength>52</uniquelength>
<term>
<termid>1</termid>
<termfrequency>0</termfrequency>
</term>
<term>
<termid>2</termid>
<termfrequency>0</termfrequency>
</term>
<term>
<termid>3</termid>
<termfrequency>0</termfrequency>
</term>
<term>
<termid>4</termid>
<termfrequency>0</termfrequency>
</term>
</stream>
<stream>
<streamid>3</streamid>
<length>58</length>
<uniquelength>54</uniquelength>
<term>
<termid>1</termid>
<termfrequency>0</termfrequency>
</term>
<term>
<termid>2</termid>
<termfrequency>0</termfrequency>
</term>
<term>
<termid>3</termid>
<termfrequency>0</termfrequency>
</term>
<term>
<termid>4</termid>
<termfrequency>0</termfrequency>
</term>
</stream>
</doc>
<doc>
<docid>241734</docid>
<label>0</label>
<stream>
<streamid>1</streamid>
<length>4</length>
<uniquelength>4</uniquelength>
<term>
<termid>1</termid>
<termfrequency>0</termfrequency>
</term>
<term>
<termid>2</termid>
<termfrequency>0</termfrequency>
</term>
<term>
<termid>3</termid>
<termfrequency>0</termfrequency>
</term>
<term>
<termid>4</termid>
<termfrequency>0</termfrequency>
</term>
</stream>
<stream>
<streamid>2</streamid>
<length>118</length>
<uniquelength>55</uniquelength>
<term>
<termid>1</termid>
<termfrequency>0</termfrequency>
</term>
<term>
<termid>2</termid>
<termfrequency>0</termfrequency>
</term>
<term>
<termid>3</termid>
<termfrequency>0</termfrequency>
</term>
<term>
<termid>4</termid>
<termfrequency>0</termfrequency>
</term>
</stream>
<stream>
<streamid>3</streamid>
<length>122</length>
<uniquelength>56</uniquelength>
<term>
<termid>1</termid>
<termfrequency>0</termfrequency>
</term>
<term>
<termid>2</termid>
<termfrequency>0</termfrequency>
</term>
<term>
<termid>3</termid>
<termfrequency>0</termfrequency>
</term>
<term>
<termid>4</termid>
<termfrequency>0</termfrequency>
</term>
</stream>
</doc>
<doc>
<docid>244413</docid>
<label>0</label>
<stream>
<streamid>1</streamid>
<length>6</length>
<uniquelength>5</uniquelength>
<term>
<termid>1</termid>
<termfrequency>0</termfrequency>
</term>
<term>
<termid>2</termid>
<termfrequency>0</termfrequency>
</term>
<term>
<termid>3</termid>
<termfrequency>0</termfrequency>
</term>
<term>
<termid>4</termid>
<termfrequency>0</termfrequency>
</term>
</stream>
<stream>
<streamid>2</streamid>
<length>0</length>
<uniquelength>0</uniquelength>
<term>
<termid>1</termid>
<termfrequency>0</termfrequency>
</term>
<term>
<termid>2</termid>
<termfrequency>0</termfrequency>
</term>
<term>
<termid>3</termid>
<termfrequency>0</termfrequency>
</term>
<term>
<termid>4</termid>
<termfrequency>0</termfrequency>
</term>
</stream>
<stream>
<streamid>3</streamid>
<length>6</length>
<uniquelength>5</uniquelength>
<term>
<termid>1</termid>
<termfrequency>0</termfrequency>
</term>
<term>
<termid>2</termid>
<termfrequency>0</termfrequency>
</term>
<term>
<termid>3</termid>
<termfrequency>0</termfrequency>
</term>
<term>
<termid>4</termid>
<termfrequency>0</termfrequency>
</term>
</stream>
</doc>
<doc>
<docid>246161</docid>
<label>0</label>
<stream>
<streamid>1</streamid>
<length>3</length>
<uniquelength>3</uniquelength>
<term>
<termid>1</termid>
<termfrequency>0</termfrequency>
</term>
<term>
<termid>2</termid>
<termfrequency>0</termfrequency>
</term>
<term>
<termid>3</termid>
<termfrequency>0</termfrequency>
</term>
<term>
<termid>4</termid>
<termfrequency>0</termfrequency>
</term>
</stream>
<stream>
<streamid>2</streamid>
<length>0</length>
<uniquelength>0</uniquelength>
<term>
<termid>1</termid>
<termfrequency>0</termfrequency>
</term>
<term>
<termid>2</termid>
<termfrequency>0</termfrequency>
</term>
<term>
<termid>3</termid>
<termfrequency>0</termfrequency>
</term>
<term>
<termid>4</termid>
<termfrequency>0</termfrequency>
</term>
</stream>
<stream>
<streamid>3</streamid>
<length>3</length>
<uniquelength>3</uniquelength>
<term>
<termid>1</termid>
<termfrequency>0</termfrequency>
</term>
<term>
<termid>2</termid>
<termfrequency>0</termfrequency>
</term>
<term>
<termid>3</termid>
<termfrequency>0</termfrequency>
</term>
<term>
<termid>4</termid>
<termfrequency>0</termfrequency>
</term>
</stream>
</doc>
<doc>
<docid>264063</docid>
<label>0</label>
<stream>
<streamid>1</streamid>
<length>8</length>
<uniquelength>8</uniquelength>
<term>
<termid>1</termid>
<termfrequency>0</termfrequency>
</term>
<term>
<termid>2</termid>
<termfrequency>0</termfrequency>
</term>
<term>
<termid>3</termid>
<termfrequency>0</termfrequency>
</term>
<term>
<termid>4</termid>
<termfrequency>0</termfrequency>
</term>
</stream>
<stream>
<streamid>2</streamid>
<length>34</length>
<uniquelength>27</uniquelength>
<term>
<termid>1</termid>
<termfrequency>0</termfrequency>
</term>
<term>
<termid>2</termid>
<termfrequency>0</termfrequency>
</term>
<term>
<termid>3</termid>
<termfrequency>0</termfrequency>
</term>
<term>
<termid>4</termid>
<termfrequency>0</termfrequency>
</term>
</stream>
<stream>
<streamid>3</streamid>
<length>42</length>
<uniquelength>28</uniquelength>
<term>
<termid>1</termid>
<termfrequency>0</termfrequency>
</term>
<term>
<termid>2</termid>
<termfrequency>0</termfrequency>
</term>
<term>
<termid>3</termid>
<termfrequency>0</termfrequency>
</term>
<term>
<termid>4</termid>
<termfrequency>0</termfrequency>
</term>
</stream>
</doc>
<doc>
<docid>264659</docid>
<label>0</label>
<stream>
<streamid>1</streamid>
<length>8</length>
<uniquelength>8</uniquelength>
<term>
<termid>1</termid>
<termfrequency>0</termfrequency>
</term>
<term>
<termid>2</termid>
<termfrequency>0</termfrequency>
</term>
<term>
<termid>3</termid>
<termfrequency>0</termfrequency>
</term>
<term>
<termid>4</termid>
<termfrequency>0</termfrequency>
</term>
</stream>
<stream>
<streamid>2</streamid>
<length>0</length>
<uniquelength>0</uniquelength>
<term>
<termid>1</termid>
<termfrequency>0</termfrequency>
</term>
<term>
<termid>2</termid>
<termfrequency>0</termfrequency>
</term>
<term>
<termid>3</termid>
<termfrequency>0</termfrequency>
</term>
<term>
<termid>4</termid>
<termfrequency>0</termfrequency>
</term>
</stream>
<stream>
<streamid>3</streamid>
<length>8</length>
<uniquelength>8</uniquelength>
<term>
<termid>1</termid>
<termfrequency>0</termfrequency>
</term>
<term>
<termid>2</termid>
<termfrequency>0</termfrequency>
</term>
<term>
<termid>3</termid>
<termfrequency>0</termfrequency>
</term>
<term>
<termid>4</termid>
<termfrequency>0</termfrequency>
</term>
</stream>
</doc>
<doc>
<docid>276255</docid>
<label>0</label>
<stream>
<streamid>1</streamid>
<length>7</length>
<uniquelength>7</uniquelength>
<term>
<termid>1</termid>
<termfrequency>0</termfrequency>
</term>
<term>
<termid>2</termid>
<termfrequency>0</termfrequency>
</term>
<term>
<termid>3</termid>
<termfrequency>0</termfrequency>
</term>
<term>
<termid>4</termid>
<termfrequency>0</termfrequency>
</term>
</stream>
<stream>
<streamid>2</streamid>
<length>69</length>
<uniquelength>48</uniquelength>
<term>
<termid>1</termid>
<termfrequency>0</termfrequency>
</term>
<term>
<termid>2</termid>
<termfrequency>0</termfrequency>
</term>
<term>
<termid>3</termid>
<termfrequency>0</termfrequency>
</term>
<term>
<termid>4</termid>
<termfrequency>0</termfrequency>
</term>
</stream>
<stream>
<streamid>3</streamid>
<length>76</length>
<uniquelength>49</uniquelength>
<term>
<termid>1</termid>
<termfrequency>0</termfrequency>
</term>
<term>
<termid>2</termid>
<termfrequency>0</termfrequency>
</term>
<term>
<termid>3</termid>
<termfrequency>0</termfrequency>
</term>
<term>
<termid>4</termid>
<termfrequency>0</termfrequency>
</term>
</stream>
</doc>
<doc>
<docid>286484</docid>
<label>0</label>
<stream>
<streamid>1</streamid>
<length>4</length>
<uniquelength>4</uniquelength>
<term>
<termid>1</termid>
<termfrequency>0</termfrequency>
</term>
<term>
<termid>2</termid>
<termfrequency>0</termfrequency>
</term>
<term>
<termid>3</termid>
<termfrequency>0</termfrequency>
</term>
<term>
<termid>4</termid>
<termfrequency>0</termfrequency>
</term>
</stream>
<stream>
<streamid>2</streamid>
<length>0</length>
<uniquelength>0</uniquelength>
<term>
<termid>1</termid>
<termfrequency>0</termfrequency>
</term>
<term>
<termid>2</termid>
<termfrequency>0</termfrequency>
</term>
<term>
<termid>3</termid>
<termfrequency>0</termfrequency>
</term>
<term>
<termid>4</termid>
<termfrequency>0</termfrequency>
</term>
</stream>
<stream>
<streamid>3</streamid>
<length>4</length>
<uniquelength>4</uniquelength>
<term>
<termid>1</termid>
<termfrequency>0</termfrequency>
</term>
<term>
<termid>2</termid>
<termfrequency>0</termfrequency>
</term>
<term>
<termid>3</termid>
<termfrequency>0</termfrequency>
</term>
<term>
<termid>4</termid>
<termfrequency>0</termfrequency>
</term>
</stream>
</doc>
<doc>
<docid>286485</docid>
<label>0</label>
<stream>
<streamid>1</streamid>
<length>4</length>
<uniquelength>4</uniquelength>
<term>
<termid>1</termid>
<termfrequency>0</termfrequency>
</term>
<term>
<termid>2</termid>
<termfrequency>0</termfrequency>
</term>
<term>
<termid>3</termid>
<termfrequency>0</termfrequency>
</term>
<term>
<termid>4</termid>
<termfrequency>0</termfrequency>
</term>
</stream>
<stream>
<streamid>2</streamid>
<length>0</length>
<uniquelength>0</uniquelength>
<term>
<termid>1</termid>
<termfrequency>0</termfrequency>
</term>
<term>
<termid>2</termid>
<termfrequency>0</termfrequency>
</term>
<term>
<termid>3</termid>
<termfrequency>0</termfrequency>
</term>
<term>
<termid>4</termid>
<termfrequency>0</termfrequency>
</term>
</stream>
<stream>
<streamid>3</streamid>
<length>4</length>
<uniquelength>4</uniquelength>
<term>
<termid>1</termid>
<termfrequency>0</termfrequency>
</term>
<term>
<termid>2</termid>
<termfrequency>0</termfrequency>
</term>
<term>
<termid>3</termid>
<termfrequency>0</termfrequency>
</term>
<term>
<termid>4</termid>
<termfrequency>0</termfrequency>
</term>
</stream>
</doc>
<doc>
<docid>288957</docid>
<label>0</label>
<stream>
<streamid>1</streamid>
<length>4</length>
<uniquelength>4</uniquelength>
<term>
<termid>1</termid>
<termfrequency>0</termfrequency>
</term>
<term>
<termid>2</termid>
<termfrequency>0</termfrequency>
</term>
<term>
<termid>3</termid>
<termfrequency>0</termfrequency>
</term>
<term>
<termid>4</termid>
<termfrequency>0</termfrequency>
</term>
</stream>
<stream>
<streamid>2</streamid>
<length>0</length>
<uniquelength>0</uniquelength>
<term>
<termid>1</termid>
<termfrequency>0</termfrequency>
</term>
<term>
<termid>2</termid>
<termfrequency>0</termfrequency>
</term>
<term>
<termid>3</termid>
<termfrequency>0</termfrequency>
</term>
<term>
<termid>4</termid>
<termfrequency>0</termfrequency>
</term>
</stream>
<stream>
<streamid>3</streamid>
<length>4</length>
<uniquelength>4</uniquelength>
<term>
<termid>1</termid>
<termfrequency>0</termfrequency>
</term>
<term>
<termid>2</termid>
<termfrequency>0</termfrequency>
</term>
<term>
<termid>3</termid>
<termfrequency>0</termfrequency>
</term>
<term>
<termid>4</termid>
<termfrequency>0</termfrequency>
</term>
</stream>
</doc>
<doc>
<docid>14466</docid>
<label>0</label>
<stream>
<streamid>1</streamid>
<length>7</length>
<uniquelength>7</uniquelength>
<term>
<termid>1</termid>
<termfrequency>0</termfrequency>
</term>
<term>
<termid>2</termid>
<termfrequency>0</termfrequency>
</term>
<term>
<termid>3</termid>
<termfrequency>0</termfrequency>
</term>
<term>
<termid>4</termid>
<termfrequency>0</termfrequency>
</term>
</stream>
<stream>
<streamid>2</streamid>
<length>195</length>
<uniquelength>123</uniquelength>
<term>
<termid>1</termid>
<termfrequency>0</termfrequency>
</term>
<term>
<termid>2</termid>
<termfrequency>0</termfrequency>
</term>
<term>
<termid>3</termid>
<termfrequency>0</termfrequency>
</term>
<term>
<termid>4</termid>
<termfrequency>0</termfrequency>
</term>
</stream>
<stream>
<streamid>3</streamid>
<length>202</length>
<uniquelength>125</uniquelength>
<term>
<termid>1</termid>
<termfrequency>0</termfrequency>
</term>
<term>
<termid>2</termid>
<termfrequency>0</termfrequency>
</term>
<term>
<termid>3</termid>
<termfrequency>0</termfrequency>
</term>
<term>
<termid>4</termid>
<termfrequency>0</termfrequency>
</term>
</stream>
</doc>
<doc>
<docid>291173</docid>
<label>1</label>
<stream>
<streamid>1</streamid>
<length>6</length>
<uniquelength>6</uniquelength>
<term>
<termid>1</termid>
<termfrequency>0</termfrequency>
</term>
<term>
<termid>2</termid>
<termfrequency>0</termfrequency>
</term>
<term>
<termid>3</termid>
<termfrequency>0</termfrequency>
</term>
<term>
<termid>4</termid>
<termfrequency>0</termfrequency>
</term>
</stream>
<stream>
<streamid>2</streamid>
<length>106</length>
<uniquelength>96</uniquelength>
<term>
<termid>1</termid>
<termfrequency>0</termfrequency>
</term>
<term>
<termid>2</termid>
<termfrequency>0</termfrequency>
</term>
<term>
<termid>3</termid>
<termfrequency>0</termfrequency>
</term>
<term>
<termid>4</termid>
<termfrequency>0</termfrequency>
</term>
</stream>
<stream>
<streamid>3</streamid>
<length>112</length>
<uniquelength>97</uniquelength>
<term>
<termid>1</termid>
<termfrequency>0</termfrequency>
</term>
<term>
<termid>2</termid>
<termfrequency>0</termfrequency>
</term>
<term>
<termid>3</termid>
<termfrequency>0</termfrequency>
</term>
<term>
<termid>4</termid>
<termfrequency>0</termfrequency>
</term>
</stream>
</doc>
<doc>
<docid>57339</docid>
<label>1</label>
<stream>
<streamid>1</streamid>
<length>2</length>
<uniquelength>2</uniquelength>
<term>
<termid>1</termid>
<termfrequency>0</termfrequency>
</term>
<term>
<termid>2</termid>
<termfrequency>0</termfrequency>
</term>
<term>
<termid>3</termid>
<termfrequency>0</termfrequency>
</term>
<term>
<termid>4</termid>
<termfrequency>0</termfrequency>
</term>
</stream>
<stream>
<streamid>2</streamid>
<length>19</length>
<uniquelength>17</uniquelength>
<term>
<termid>1</termid>
<termfrequency>0</termfrequency>
</term>
<term>
<termid>2</termid>
<termfrequency>0</termfrequency>
</term>
<term>
<termid>3</termid>
<termfrequency>0</termfrequency>
</term>
<term>
<termid>4</termid>
<termfrequency>0</termfrequency>
</term>
</stream>
<stream>
<streamid>3</streamid>
<length>21</length>
<uniquelength>17</uniquelength>
<term>
<termid>1</termid>
<termfrequency>0</termfrequency>
</term>
<term>
<termid>2</termid>
<termfrequency>0</termfrequency>
</term>
<term>
<termid>3</termid>
<termfrequency>0</termfrequency>
</term>
<term>
<termid>4</termid>
<termfrequency>0</termfrequency>
</term>
</stream>
</doc>
<doc>
<docid>63505</docid>
<label>1</label>
<stream>
<streamid>1</streamid>
<length>8</length>
<uniquelength>8</uniquelength>
<term>
<termid>1</termid>
<termfrequency>0</termfrequency>
</term>
<term>
<termid>2</termid>
<termfrequency>0</termfrequency>
</term>
<term>
<termid>3</termid>
<termfrequency>0</termfrequency>
</term>
<term>
<termid>4</termid>
<termfrequency>0</termfrequency>
</term>
</stream>
<stream>
<streamid>2</streamid>
<length>65</length>
<uniquelength>51</uniquelength>
<term>
<termid>1</termid>
<termfrequency>0</termfrequency>
</term>
<term>
<termid>2</termid>
<termfrequency>0</termfrequency>
</term>
<term>
<termid>3</termid>
<termfrequency>0</termfrequency>
</term>
<term>
<termid>4</termid>
<termfrequency>0</termfrequency>
</term>
</stream>
<stream>
<streamid>3</streamid>
<length>73</length>
<uniquelength>54</uniquelength>
<term>
<termid>1</termid>
<termfrequency>0</termfrequency>
</term>
<term>
<termid>2</termid>
<termfrequency>0</termfrequency>
</term>
<term>
<termid>3</termid>
<termfrequency>0</termfrequency>
</term>
<term>
<termid>4</termid>
<termfrequency>0</termfrequency>
</term>
</stream>
</doc>
<doc>
<docid>63892</docid>
<label>0</label>
<stream>
<streamid>1</streamid>
<length>12</length>
<uniquelength>12</uniquelength>
<term>
<termid>1</termid>
<termfrequency>0</termfrequency>
</term>
<term>
<termid>2</termid>
<termfrequency>0</termfrequency>
</term>
<term>
<termid>3</termid>
<termfrequency>0</termfrequency>
</term>
<term>
<termid>4</termid>
<termfrequency>0</termfrequency>
</term>
</stream>
<stream>
<streamid>2</streamid>
<length>84</length>
<uniquelength>53</uniquelength>
<term>
<termid>1</termid>
<termfrequency>0</termfrequency>
</term>
<term>
<termid>2</termid>
<termfrequency>0</termfrequency>
</term>
<term>
<termid>3</termid>
<termfrequency>0</termfrequency>
</term>
<term>
<termid>4</termid>
<termfrequency>0</termfrequency>
</term>
</stream>
<stream>
<streamid>3</streamid>
<length>96</length>
<uniquelength>54</uniquelength>
<term>
<termid>1</termid>
<termfrequency>0</termfrequency>
</term>
<term>
<termid>2</termid>
<termfrequency>0</termfrequency>
</term>
<term>
<termid>3</termid>
<termfrequency>0</termfrequency>
</term>
<term>
<termid>4</termid>
<termfrequency>0</termfrequency>
</term>
</stream>
</doc>
<doc>
<docid>64523</docid>
<label>0</label>
<stream>
<streamid>1</streamid>
<length>7</length>
<uniquelength>7</uniquelength>
<term>
<termid>1</termid>
<termfrequency>0</termfrequency>
</term>
<term>
<termid>2</termid>
<termfrequency>0</termfrequency>
</term>
<term>
<termid>3</termid>
<termfrequency>0</termfrequency>
</term>
<term>
<termid>4</termid>
<termfrequency>0</termfrequency>
</term>
</stream>
<stream>
<streamid>2</streamid>
<length>0</length>
<uniquelength>0</uniquelength>
<term>
<termid>1</termid>
<termfrequency>0</termfrequency>
</term>
<term>
<termid>2</termid>
<termfrequency>0</termfrequency>
</term>
<term>
<termid>3</termid>
<termfrequency>0</termfrequency>
</term>
<term>
<termid>4</termid>
<termfrequency>0</termfrequency>
</term>
</stream>
<stream>
<streamid>3</streamid>
<length>7</length>
<uniquelength>7</uniquelength>
<term>
<termid>1</termid>
<termfrequency>0</termfrequency>
</term>
<term>
<termid>2</termid>
<termfrequency>0</termfrequency>
</term>
<term>
<termid>3</termid>
<termfrequency>0</termfrequency>
</term>
<term>
<termid>4</termid>
<termfrequency>0</termfrequency>
</term>
</stream>
</doc>
<doc>
<docid>303689</docid>
<label>0</label>
<stream>
<streamid>1</streamid>
<length>8</length>
<uniquelength>8</uniquelength>
<term>
<termid>1</termid>
<termfrequency>0</termfrequency>
</term>
<term>
<termid>2</termid>
<termfrequency>0</termfrequency>
</term>
<term>
<termid>3</termid>
<termfrequency>0</termfrequency>
</term>
<term>
<termid>4</termid>
<termfrequency>0</termfrequency>
</term>
</stream>
<stream>
<streamid>2</streamid>
<length>61</length>
<uniquelength>56</uniquelength>
<term>
<termid>1</termid>
<termfrequency>0</termfrequency>
</term>
<term>
<termid>2</termid>
<termfrequency>0</termfrequency>
</term>
<term>
<termid>3</termid>
<termfrequency>0</termfrequency>
</term>
<term>
<termid>4</termid>
<termfrequency>0</termfrequency>
</term>
</stream>
<stream>
<streamid>3</streamid>
<length>69</length>
<uniquelength>60</uniquelength>
<term>
<termid>1</termid>
<termfrequency>0</termfrequency>
</term>
<term>
<termid>2</termid>
<termfrequency>0</termfrequency>
</term>
<term>
<termid>3</termid>
<termfrequency>0</termfrequency>
</term>
<term>
<termid>4</termid>
<termfrequency>0</termfrequency>
</term>
</stream>
</doc>
<doc>
<docid>120313</docid>
<label>0</label>
<stream>
<streamid>1</streamid>
<length>3</length>
<uniquelength>3</uniquelength>
<term>
<termid>1</termid>
<termfrequency>0</termfrequency>
</term>
<term>
<termid>2</termid>
<termfrequency>0</termfrequency>
</term>
<term>
<termid>3</termid>
<termfrequency>0</termfrequency>
</term>
<term>
<termid>4</termid>
<termfrequency>0</termfrequency>
</term>
</stream>
<stream>
<streamid>2</streamid>
<length>0</length>
<uniquelength>0</uniquelength>
<term>
<termid>1</termid>
<termfrequency>0</termfrequency>
</term>
<term>
<termid>2</termid>
<termfrequency>0</termfrequency>
</term>
<term>
<termid>3</termid>
<termfrequency>0</termfrequency>
</term>
<term>
<termid>4</termid>
<termfrequency>0</termfrequency>
</term>
</stream>
<stream>
<streamid>3</streamid>
<length>3</length>
<uniquelength>3</uniquelength>
<term>
<termid>1</termid>
<termfrequency>0</termfrequency>
</term>
<term>
<termid>2</termid>
<termfrequency>0</termfrequency>
</term>
<term>
<termid>3</termid>
<termfrequency>0</termfrequency>
</term>
<term>
<termid>4</termid>
<termfrequency>0</termfrequency>
</term>
</stream>
</doc>
<doc>
<docid>307686</docid>
<label>0</label>
<stream>
<streamid>1</streamid>
<length>3</length>
<uniquelength>3</uniquelength>
<term>
<termid>1</termid>
<termfrequency>0</termfrequency>
</term>
<term>
<termid>2</termid>
<termfrequency>0</termfrequency>
</term>
<term>
<termid>3</termid>
<termfrequency>0</termfrequency>
</term>
<term>
<termid>4</termid>
<termfrequency>0</termfrequency>
</term>
</stream>
<stream>
<streamid>2</streamid>
<length>61</length>
<uniquelength>49</uniquelength>
<term>
<termid>1</termid>
<termfrequency>0</termfrequency>
</term>
<term>
<termid>2</termid>
<termfrequency>0</termfrequency>
</term>
<term>
<termid>3</termid>
<termfrequency>0</termfrequency>
</term>
<term>
<termid>4</termid>
<termfrequency>0</termfrequency>
</term>
</stream>
<stream>
<streamid>3</streamid>
<length>64</length>
<uniquelength>49</uniquelength>
<term>
<termid>1</termid>
<termfrequency>0</termfrequency>
</term>
<term>
<termid>2</termid>
<termfrequency>0</termfrequency>
</term>
<term>
<termid>3</termid>
<termfrequency>0</termfrequency>
</term>
<term>
<termid>4</termid>
<termfrequency>0</termfrequency>
</term>
</stream>
</doc>
<doc>
<docid>310477</docid>
<label>0</label>
<stream>
<streamid>1</streamid>
<length>6</length>
<uniquelength>6</uniquelength>
<term>
<termid>1</termid>
<termfrequency>0</termfrequency>
</term>
<term>
<termid>2</termid>
<termfrequency>0</termfrequency>
</term>
<term>
<termid>3</termid>
<termfrequency>0</termfrequency>
</term>
<term>
<termid>4</termid>
<termfrequency>0</termfrequency>
</term>
</stream>
<stream>
<streamid>2</streamid>
<length>0</length>
<uniquelength>0</uniquelength>
<term>
<termid>1</termid>
<termfrequency>0</termfrequency>
</term>
<term>
<termid>2</termid>
<termfrequency>0</termfrequency>
</term>
<term>
<termid>3</termid>
<termfrequency>0</termfrequency>
</term>
<term>
<termid>4</termid>
<termfrequency>0</termfrequency>
</term>
</stream>
<stream>
<streamid>3</streamid>
<length>6</length>
<uniquelength>6</uniquelength>
<term>
<termid>1</termid>
<termfrequency>0</termfrequency>
</term>
<term>
<termid>2</termid>
<termfrequency>0</termfrequency>
</term>
<term>
<termid>3</termid>
<termfrequency>0</termfrequency>
</term>
<term>
<termid>4</termid>
<termfrequency>0</termfrequency>
</term>
</stream>
</doc>
<doc>
<docid>312085</docid>
<label>0</label>
<stream>
<streamid>1</streamid>
<length>6</length>
<uniquelength>6</uniquelength>
<term>
<termid>1</termid>
<termfrequency>0</termfrequency>
</term>
<term>
<termid>2</termid>
<termfrequency>0</termfrequency>
</term>
<term>
<termid>3</termid>
<termfrequency>0</termfrequency>
</term>
<term>
<termid>4</termid>
<termfrequency>0</termfrequency>
</term>
</stream>
<stream>
<streamid>2</streamid>
<length>105</length>
<uniquelength>76</uniquelength>
<term>
<termid>1</termid>
<termfrequency>0</termfrequency>
</term>
<term>
<termid>2</termid>
<termfrequency>0</termfrequency>
</term>
<term>
<termid>3</termid>
<termfrequency>0</termfrequency>
</term>
<term>
<termid>4</termid>
<termfrequency>0</termfrequency>
</term>
</stream>
<stream>
<streamid>3</streamid>
<length>111</length>
<uniquelength>79</uniquelength>
<term>
<termid>1</termid>
<termfrequency>0</termfrequency>
</term>
<term>
<termid>2</termid>
<termfrequency>0</termfrequency>
</term>
<term>
<termid>3</termid>
<termfrequency>0</termfrequency>
</term>
<term>
<termid>4</termid>
<termfrequency>0</termfrequency>
</term>
</stream>
</doc>
<doc>
<docid>314267</docid>
<label>0</label>
<stream>
<streamid>1</streamid>
<length>6</length>
<uniquelength>6</uniquelength>
<term>
<termid>1</termid>
<termfrequency>0</termfrequency>
</term>
<term>
<termid>2</termid>
<termfrequency>0</termfrequency>
</term>
<term>
<termid>3</termid>
<termfrequency>0</termfrequency>
</term>
<term>
<termid>4</termid>
<termfrequency>0</termfrequency>
</term>
</stream>
<stream>
<streamid>2</streamid>
<length>119</length>
<uniquelength>71</uniquelength>
<term>
<termid>1</termid>
<termfrequency>0</termfrequency>
</term>
<term>
<termid>2</termid>
<termfrequency>0</termfrequency>
</term>
<term>
<termid>3</termid>
<termfrequency>0</termfrequency>
</term>
<term>
<termid>4</termid>
<termfrequency>0</termfrequency>
</term>
</stream>
<stream>
<streamid>3</streamid>
<length>125</length>
<uniquelength>73</uniquelength>
<term>
<termid>1</termid>
<termfrequency>0</termfrequency>
</term>
<term>
<termid>2</termid>
<termfrequency>0</termfrequency>
</term>
<term>
<termid>3</termid>
<termfrequency>0</termfrequency>
</term>
<term>
<termid>4</termid>
<termfrequency>0</termfrequency>
</term>
</stream>
</doc>
<doc>
<docid>317461</docid>
<label>0</label>
<stream>
<streamid>1</streamid>
<length>6</length>
<uniquelength>6</uniquelength>
<term>
<termid>1</termid>
<termfrequency>0</termfrequency>
</term>
<term>
<termid>2</termid>
<termfrequency>0</termfrequency>
</term>
<term>
<termid>3</termid>
<termfrequency>0</termfrequency>
</term>
<term>
<termid>4</termid>
<termfrequency>0</termfrequency>
</term>
</stream>
<stream>
<streamid>2</streamid>
<length>0</length>
<uniquelength>0</uniquelength>
<term>
<termid>1</termid>
<termfrequency>0</termfrequency>
</term>
<term>
<termid>2</termid>
<termfrequency>0</termfrequency>
</term>
<term>
<termid>3</termid>
<termfrequency>0</termfrequency>
</term>
<term>
<termid>4</termid>
<termfrequency>0</termfrequency>
</term>
</stream>
<stream>
<streamid>3</streamid>
<length>6</length>
<uniquelength>6</uniquelength>
<term>
<termid>1</termid>
<termfrequency>0</termfrequency>
</term>
<term>
<termid>2</termid>
<termfrequency>0</termfrequency>
</term>
<term>
<termid>3</termid>
<termfrequency>0</termfrequency>
</term>
<term>
<termid>4</termid>
<termfrequency>0</termfrequency>
</term>
</stream>
</doc>
<doc>
<docid>324665</docid>
<label>0</label>
<stream>
<streamid>1</streamid>
<length>5</length>
<uniquelength>5</uniquelength>
<term>
<termid>1</termid>
<termfrequency>0</termfrequency>
</term>
<term>
<termid>2</termid>
<termfrequency>0</termfrequency>
</term>
<term>
<termid>3</termid>
<termfrequency>0</termfrequency>
</term>
<term>
<termid>4</termid>
<termfrequency>0</termfrequency>
</term>
</stream>
<stream>
<streamid>2</streamid>
<length>0</length>
<uniquelength>0</uniquelength>
<term>
<termid>1</termid>
<termfrequency>0</termfrequency>
</term>
<term>
<termid>2</termid>
<termfrequency>0</termfrequency>
</term>
<term>
<termid>3</termid>
<termfrequency>0</termfrequency>
</term>
<term>
<termid>4</termid>
<termfrequency>0</termfrequency>
</term>
</stream>
<stream>
<streamid>3</streamid>
<length>5</length>
<uniquelength>5</uniquelength>
<term>
<termid>1</termid>
<termfrequency>0</termfrequency>
</term>
<term>
<termid>2</termid>
<termfrequency>0</termfrequency>
</term>
<term>
<termid>3</termid>
<termfrequency>0</termfrequency>
</term>
<term>
<termid>4</termid>
<termfrequency>0</termfrequency>
</term>
</stream>
</doc>
<doc>
<docid>75964</docid>
<label>0</label>
<stream>
<streamid>1</streamid>
<length>10</length>
<uniquelength>10</uniquelength>
<term>
<termid>1</termid>
<termfrequency>0</termfrequency>
</term>
<term>
<termid>2</termid>
<termfrequency>0</termfrequency>
</term>
<term>
<termid>3</termid>
<termfrequency>0</termfrequency>
</term>
<term>
<termid>4</termid>
<termfrequency>0</termfrequency>
</term>
</stream>
<stream>
<streamid>2</streamid>
<length>98</length>
<uniquelength>72</uniquelength>
<term>
<termid>1</termid>
<termfrequency>0</termfrequency>
</term>
<term>
<termid>2</termid>
<termfrequency>0</termfrequency>
</term>
<term>
<termid>3</termid>
<termfrequency>0</termfrequency>
</term>
<term>
<termid>4</termid>
<termfrequency>0</termfrequency>
</term>
</stream>
<stream>
<streamid>3</streamid>
<length>108</length>
<uniquelength>74</uniquelength>
<term>
<termid>1</termid>
<termfrequency>0</termfrequency>
</term>
<term>
<termid>2</termid>
<termfrequency>0</termfrequency>
</term>
<term>
<termid>3</termid>
<termfrequency>0</termfrequency>
</term>
<term>
<termid>4</termid>
<termfrequency>0</termfrequency>
</term>
</stream>
</doc>
<doc>
<docid>80106</docid>
<label>0</label>
<stream>
<streamid>1</streamid>
<length>5</length>
<uniquelength>5</uniquelength>
<term>
<termid>1</termid>
<termfrequency>0</termfrequency>
</term>
<term>
<termid>2</termid>
<termfrequency>0</termfrequency>
</term>
<term>
<termid>3</termid>
<termfrequency>0</termfrequency>
</term>
<term>
<termid>4</termid>
<termfrequency>0</termfrequency>
</term>
</stream>
<stream>
<streamid>2</streamid>
<length>0</length>
<uniquelength>0</uniquelength>
<term>
<termid>1</termid>
<termfrequency>0</termfrequency>
</term>
<term>
<termid>2</termid>
<termfrequency>0</termfrequency>
</term>
<term>
<termid>3</termid>
<termfrequency>0</termfrequency>
</term>
<term>
<termid>4</termid>
<termfrequency>0</termfrequency>
</term>
</stream>
<stream>
<streamid>3</streamid>
<length>5</length>
<uniquelength>5</uniquelength>
<term>
<termid>1</termid>
<termfrequency>0</termfrequency>
</term>
<term>
<termid>2</termid>
<termfrequency>0</termfrequency>
</term>
<term>
<termid>3</termid>
<termfrequency>0</termfrequency>
</term>
<term>
<termid>4</termid>
<termfrequency>0</termfrequency>
</term>
</stream>
</doc>
<doc>
<docid>339678</docid>
<label>0</label>
<stream>
<streamid>1</streamid>
<length>4</length>
<uniquelength>4</uniquelength>
<term>
<termid>1</termid>
<termfrequency>0</termfrequency>
</term>
<term>
<termid>2</termid>
<termfrequency>0</termfrequency>
</term>
<term>
<termid>3</termid>
<termfrequency>0</termfrequency>
</term>
<term>
<termid>4</termid>
<termfrequency>0</termfrequency>
</term>
</stream>
<stream>
<streamid>2</streamid>
<length>0</length>
<uniquelength>0</uniquelength>
<term>
<termid>1</termid>
<termfrequency>0</termfrequency>
</term>
<term>
<termid>2</termid>
<termfrequency>0</termfrequency>
</term>
<term>
<termid>3</termid>
<termfrequency>0</termfrequency>
</term>
<term>
<termid>4</termid>
<termfrequency>0</termfrequency>
</term>
</stream>
<stream>
<streamid>3</streamid>
<length>4</length>
<uniquelength>4</uniquelength>
<term>
<termid>1</termid>
<termfrequency>0</termfrequency>
</term>
<term>
<termid>2</termid>
<termfrequency>0</termfrequency>
</term>
<term>
<termid>3</termid>
<termfrequency>0</termfrequency>
</term>
<term>
<termid>4</termid>
<termfrequency>0</termfrequency>
</term>
</stream>
</doc>
</docinfo>
</query>
